Workbook
Name NC_ARO_Carrying_Amount: #REF!
Name Waehrung: #REF!

Sheet Main
B1: Sq.ft. | C1: Sq.m.
A2: REU | B2: IN-CHEK2
A3: Chargeable Office Area | B3: 9515 | C3: =B3/10.764 -> 883.96507
A4: Agreement Start Date | B4: 46113
A5: Agreement End Date | B5: 47938
A6: Agreement Period | B6: =(B5-B4)/365 -> 5
A7: Quoted Rentals | B7: 120
A8: Quoted CAM | B8: 15.48
A9: Security Deposit | B9: 11418000
A10: Capex | B10: 43000000
A11: PM cost Over lease period | B11: 2500000
A12: Cost of Capital | B12: 0.105
A13: Imputed Interest | B13: 0.0711
A14: Escalation Clause Rent | B14: 15% every 3 years
A15: Escalation Clause CAM | B15: 5% every years
A16: No. of 4 wheelers | B16: 80
A17: Rate per 4 wheeler | B17: 1500
A18: No. of 2 wheelers | B18: 50
A19: Rate per 2 wheeler | B19: 1000

Sheet Rent Calculation
B5: RENTAL CALCULATION FOR NEW LEASE | I5: Ex. Rate | J5: 105.02
F6: 10.764 | I6: 10.764
B7: Sr. No. | C7: Preferences by SRE | F7: As on 01/01/2026 | G7: =+F7 -> As on 01/01/2026 | I7: =F7 -> As on 01/01/2026 | J7: =I7 -> As on 01/01/2026
F8: INR | I8: €
B9: General Description | F9: Per sq. ft | G9: Per sq. Mtr | I9: Per sq. ft | J9: Per sq. Mtr
B10: 1 | C10: Name of the Lessor | F10: Chennai | I10: =+F10 -> Chennai
B11: =1+B10 -> 2 | C11: Address | I11: =+F11 -> 0
B12: =1+B11 -> 3 | C12: Age of Building in Yrs | I12: =+F12 -> 0
B13: =1+B12 -> 4 | C13: Age of fit outs in Yrs
B14: =1+B13 -> 5 | C14: Total Floors | F14: 6th floor | I14: =+F14 -> 6th floor
B15: =1+B14 -> 6 | C15: Floor available for Lease | I15: =+F15 -> 0
B16: =1+B15 -> 7 | C16: Distance from main City in kms
B17: =1+B16 -> 8 | C17: Type of Shell | F17: Warm Shell | I17: =+F17 -> Warm Shell
B18: =1+B17 -> 9 | C18: Floor considered for current Lease | F18: =F15 -> 0 | I18: =+F18 -> 0
B19: =1+B18 -> 10 | C19: Consultant
B20: =1+B19 -> 11 | C20: Assumed capital value in Rs. (Ready Receokner Rate) | I20: =+F20/J5 -> 0 | J20: =+G20/J5 -> 0
B21: =1+B20 -> 12 | C21: Chargeable office area | F21: =Main!B3 -> 9515 | G21: =F21/F6 -> 883.96507 | I21: =+F21 -> 9515 | J21: =I21/I6 -> 883.96507
B22: =1+B21 -> 13 | C22: Chargeable Utility area ( Terrace) | F22: 0 | G22: 0 | I22: =+F22 -> 0 | J22: =I22/I6 -> 0
B23: =1+B22 -> 14 | C23: Total area | F23: =+F21+F22 -> 9515 | G23: =+G21+G22 -> 883.96507 | I23: =+I21+I22 -> 9515 | J23: =+J21+J22 -> 883.96507
B24: =1+B23 -> 15 | C24: Installed Capacity - No. of Workplaces | G24: =F24 -> 0 | I24: =+F24 -> 0 | J24: =I24 -> 0
B25: =1+B24 -> 16 | C25: Carpet Area | F25: 0 | G25: =+G23*G26 -> 0 | I25: =+F25 -> 0 | J25: =+G25 -> 0
B26: =1+B25 -> 17 | C26: Efficiency in % | F26: =F25/F23 -> 0 | G26: =+F26 -> 0 | I26: =+I25/I23 -> 0 | J26: =+I26 -> 0
B27: =1+B26 -> 18 | C27: Amortization Period for Fit outs (Months) | F27: ='CAPEX and PM'!E3 -> 72 | G27: =+F27 -> 72 | I27: =+F27 -> 72 | J27: =+I27 -> 72
B28: =1+B27 -> 19 | C28: Cost of Capital (%) | F28: =Main!B12 -> 0.105 | G28: =SUM(F28) -> 0.105 | I28: =+F28 -> 0.105 | J28: =SUM(I28) -> 0.105
B29: =1+B28 -> 20 | C29: Imputed Interest on Assets (%) | F29: =Main!B13 -> 0.0711 | G29: =F29 -> 0.0711 | I29: =F29 -> 0.0711 | J29: =I29 -> 0.0711
B30: =1+B29 -> 21 | C30: Lease acquqision cost - Brokerage [as 15 days rent] | F30: 0 | G30: =F30 -> 0 | I30: =+F30/J5 -> 0 | J30: =+G30/J5 -> 0
B31: Agreed Terms with Landlord | F31: Per sq. ft | G31: Per sq. Mtr | I31: Per sq. ft | J31: Per sq. Mtr
B32: 1 | C32: Security deposit ( number of months ) | F32: =Main!B9/(Main!B3*Main!B7) -> 10 | G32: =+F32 -> 10 | I32: =+F32/$J$5 -> 0.095219958 | J32: =+I32*$I$6 -> 1.0249476
B33: =1+B32 -> 2 | C33: Maintenance Security deposit (number of months) | F33: 0 | G33: =+F33 -> 0 | I33: 0 | J33: =+I33 -> 0
B34: =1+B33 -> 3 | C34: Fitout Security deposit for rent free period | F34: 0 | G34: =F34 -> 0 | I34: =F34/J5 -> 0 | J34: =I34 -> 0
B35: =1+B34 -> 4 | C35: Advance Rent in months | F35: 0 | G35: 0 | I35: 0 | J35: 0
B36: =1+B35 -> 5 | C36: Quoted Rentals (Not negotiated) ( per Sq.ft./Sq. mtr) | F36: ='Lease Rent'!H37 -> 120 | G36: =+F36*F6 -> 1291.68 | I36: =+F36/$J$5 -> 1.1426395 | J36: =+I36*$I$6 -> 12.299372
B37: =1+B36 -> 6 | C37: Quoted Rentals Fitouts (Not negotiated) ( per Sq.ft./Sq. mtr) | G37: =F37*F3 -> 0
B38: =1+B37 -> 7 | C38: Quoted CAM (Not negotiated) ( per Sq.ft./Sq. mtr) | F38: ='Lease Rent'!J31 -> 15.48 | G38: =F38*F6 -> 166.62672 | I38: =+F38/$J$5 -> 0.1474005 | J38: =+I38*$I$6 -> 1.5866189
B39: =1+B38 -> 8 | C39: Rentals (Negotiated) ( per Sq.ft./Sq. mtr) | F39: =F36 -> 120 | G39: =F39*F6 -> 1291.68 | I39: =+F39/$J$5 -> 1.1426395 | J39: =+I39*$I$6 -> 12.299372
B40: =1+B39 -> 9 | C40: Rentals Utility (negotiated) ( per Sq.ft./Sq. mtr) | F40: 0 | G40: =F40*F6 -> 0 | I40: =+F40/$J$5 -> 0 | J40: =+I40*$I$6 -> 0
B41: =1+B40 -> 10 | C41: CAM ( Negotiated) ( per Sq.ft./Sq. mtr) | F41: =F38 -> 15.48 | G41: =F41*F6 -> 166.62672 | I41: =+F41/$J$5 -> 0.1474005 | J41: =I41*I6 -> 1.5866189
B42: =1+B41 -> 11 | C42: No. of dedicated car parks - Free | F42: 0 | G42: =+F42 -> 0 | I42: =+F42 -> 0 | J42: =+I42 -> 0
B43: =1+B42 -> 12 | C43: No. of dedicated car parks - chargeable | F43: ='Lease Rent'!D22 -> 80 | G43: =F43 -> 80 | I43: =+F43 -> 80 | J43: =I43 -> 80
B44: =1+B43 -> 13 | C44: Carpark - charges per car including Service tax | F44: ='Lease Rent'!C22 -> 1500 | G44: =F44 -> 1500 | I44: =+F44/$J$5 -> 14.282994 | J44: =I44 -> 14.282994
B45: =1+B44 -> 14 | C45: No. of dedicated 2 Wheeler parks - Free | F45: 0 | G45: =+F45 -> 0 | J45: =+I45 -> 0
B46: =1+B45 -> 15 | C46: No. of dedicated bike parks - chargeable | F46: ='Lease Rent'!D23 -> 50
B47: =1+B46 -> 16 | C47: Bikepark - charges per bike including Service tax | F47: ='Lease Rent'!C23 -> 1000
B48: =1+B47 -> 17 | C48: Escalation - Rent (after every year) | F48: =Main!B14 -> 15% every 3 years | I48: =+F48 -> 15% every 3 years
C49: Escalation - CAM (after every year) | F49: =Main!B15 -> 5% every years | I49: =F49 -> 5% every years
B50: =1+B48 -> 18 | C50: Expected date of Agreement to start | F50: ='Lease Rent'!B31 -> 46023 | I50: =F50 -> 46023
B51: =1+B50 -> 19 | C51: Expected date of Agreement to close | F51: ='Lease Rent'!C102 -> 48213 | I51: =F51 -> 48213
B52: =1+B51 -> 20 | C52: Expected date of Rent commencement | F52: =F50 -> 46023 | I52: =F52 -> 46023
B53: =1+B52 -> 21 | C53: Rent Free Period (Months) | F53: 0 | I53: =+F53 -> 0
B54: =1+B53 -> 22 | C54: Agreement Period (Months) | F54: =(F51-F50)/365*12 -> 72 | G54: =F54 -> 72 | I54: =F54 -> 72 | J54: =I54 -> 72
B55: =1+B54 -> 23 | C55: Lock in period in months | F55: 0 | G55: =F55 -> 0 | I55: =F55 -> 0 | J55: =I55 -> 0
B56: =1+B55 -> 24 | C56: Notice Period in Months | G56: =+F56 | I56: =F56 | J56: =+I56
B57: =1+B56 -> 25 | C57: Sub-Lease rent paid to LL
F58: INR | I58: €
B59: Commercials | F59: Per sq. ft | G59: Per sq. Mtr | I59: Per sq. ft | J59: Per sq. Mtr
B60: 1 | C60: Average Rental for Space, Terrrace & Signages ( per Sq.ft./Sq. mtr) | F60: =C220/F21/F54 -> 129 | G60: =+F60*F6 -> 1388.556 | I60: =+F60/$J$5 -> 1.2283375 | J60: =+I60*$I$6 -> 13.221824
B61: =1+B60 -> 2 | C61: Add : 1% Krishi Kalyan Cess ( Nett of Cenvat) | F61: 0 | G61: 0 | I61: =+F61/$J$5 -> 0 | J61: =G61/J5 -> 0
B62: =1+B61 -> 3 | C62: Target Rentals in Rs. ( per Sq.ft./Sq. mtr) per month | F62: =F60+F61 -> 129 | G62: =+G60+G61 -> 1388.556 | I62: =I60+I61 -> 1.2283375 | J62: =+J60+J61 -> 13.221824
B63: =1+B62 -> 4 | C63: Rental / Month | F63: =F62*F21 -> 1227435 | G63: =+F63 -> 1227435 | I63: =+F63/$J$5 -> 11687.631 | J63: =+I63 -> 11687.631
B64: =1+B63 -> 5 | C64: Average CAM for Space ( per Sq.ft./Sq. mtr) | F64: =I220/F21/F54 -> 17.548935 | G64: =+F64*F6 -> 188.89674 | I64: =+F64/J5 -> 0.16710089 | J64: =+I64*$I$6 -> 1.7986739
B65: =1+B64 -> 6 | C65: CAM / Month | F65: =+F64*F21 -> 166978.12 | G65: =+G64*G21*1.01 -> 168647.9 | I65: =+F65/$J$5 -> 1589.9649 | J65: =+I65 -> 1589.9649
B66: =1+B65 -> 7 | C66: Carpark Rent / Month | F66: =(+G220/F54) -> 182750 | G66: =+F66 -> 182750 | I66: =+F66/$J$5 -> 1740.1447 | J66: =G66/J5 -> 1740.1447
B67: =1+B66 -> 8 | C67: Security deposit (Refundable) | F67: =Main!B9 -> 11418000 | G67: =F67 -> 11418000 | I67: =+F67/$J$5 -> 108722.15 | J67: =G67/J5 -> 108722.15
B68: =1+B67 -> 9 | C68: Addnl.Deposit at the beginning of 4yr due to Escltn in Rent (Refundable) | F68: 0 | G68: =F68 -> 0 | I68: =+F68/$J$5 -> 0 | J68: =+G68/J5 -> 0
B69: =1+B68 -> 10 | C69: Addnl.Deposit -energy(Refundable) | F69: 500000 | G69: =+F69 -> 500000 | I69: =+F69/$J$5 -> 4760.9979 | J69: =+I69*$I$6 -> 51247.381
B70: =1+B69 -> 11 | C70: Addnl.Deposit at the beginning of 10yr due to Escltn in Rent (Refundable) | F70: 0 | I70: =+F70/$J$5 -> 0 | J70: =+I70*$I$6 -> 0
B71: =1+B70 -> 12 | C71: Maint. Service Deposit (Refundable) | F71: =F38*F23*F33 -> 0 | G71: =F71 -> 0 | I71: =+F71/$J$5 -> 0 | J71: =+I71*$I$6 -> 0
B72: =1+B71 -> 13 | C72: Power Deposit (Refundable) | F72: 0 | G72: =+F72 -> 0 | I72: =+F72/$J$5 -> 0 | J72: =+I72*$I$6 -> 0
B73: =1+B72 -> 14 | C73: Advance Rent | F73: =+F35*F63 -> 0 | G73: =G35*G63 -> 0 | I73: =+F73/$J$5 -> 0 | J73: =+I73*$I$6 -> 0
B74: =1+B73 -> 15 | C74: Opex Rate | F74: =F119 -> 699.78 | G74: 0 | I74: =+F74/J5 -> 6.6633022 | J74: =+I74*$I$6 -> 71.723785
B75: =1+B74 -> 16 | C75: CAPEX for Fit out cost per sq.ft/sq. mtr (will be actualized) | F75: =+F77/F23 -> 1471.361 | G75: =+G77/G23 -> 15837.73 | I75: =+F75/$J$5 -> 14.010293 | J75: =+I75*$I$6 -> 150.8068
B76: =1+B75 -> 17 | C76: Siemens Standard Fitout (Existing) | I76: =+F76/$J$5 -> 0 | J76: =+I76*$I$6 -> 0
B77: =1+B76 -> 18 | C77: Siemens Standard Fitout (New) | F77: ='CAPEX and PM'!B6 -> 14000000 | G77: =F77 -> 14000000 | I77: =+F77/$J$5 -> 133307.94 | J77: =+G77/J5 -> 133307.94
B78: =1+B77 -> 19 | C78: Capex over the period of lease period | F78: ='CAPEX and PM'!B37 -> 43000000 | G78: =+F78 -> 43000000 | I78: =+F78/$J$5 -> 409445.82 | J78: =+I78*$I$6 -> 4407274.8
B79: =1+B78 -> 20 | C79: PM cost over the period of lease period | F79: =+'CAPEX and PM'!B104 -> 2500000 | G79: =F79 -> 2500000 | I79: =+F79/$J$5 -> 23804.99 | J79: =+I79*$I$6 -> 256236.91
B80: =1+B79 -> 21 | C80: Asset Retirement Obligation ( Removal & Restoration Obligation) | I80: =+F80/$J$5 -> 0 | J80: =+I80*$I$6 -> 0
B81: =1+B80 -> 22 | C81: Passive Data Network (Only for add. Refinancing) | I81: =+F81/$J$5 -> 0 | J81: =+I81*$I$6 -> 0
B82: =1+B81 -> 23 | C82: Estimated Stamp Duty & Registration (One time Payment) | F82: =+G207 -> 565315.3 | G82: =+F82 -> 565315.3 | I82: =+F82/$J$5 -> 5382.9299 | J82: =G82/J5 -> 5382.9299
B83: =1+B82 -> 24 | C83: Lease acquision cost - Brokerage on warm shell (One time Payment) | F83: =+F30 -> 0 | G83: =+F83 -> 0 | I83: 4 | J83: =G83/J5 -> 0
B85: Net Rent I - Base Rent | F85: Per sq. ft | G85: Per sq. Mtr | I85: Per sq. ft | J85: Per sq. Mtr
B86: 1 | C86: Effective Rent | F86: =+F62 -> 129 | G86: =+G62 -> 1388.556 | I86: =+F86/J5 -> 1.2283375 | J86: =G86/J5 -> 13.221824
B87: =1+B86 -> 2 | C87: Effect of advance rent | F87: 0 | G87: 0 | I87: 0 | J87: 0
B88: =+B87+1 -> 3 | C88: Effect of Parking on Rent | F88: =(F66/F23) -> 19.206516 | G88: =+F88*F6 -> 206.73894 | I88: =+F88/J5 -> 0.18288437 | J88: =+I88*I6 -> 1.9685673
B89: =+B88+1 -> 4 | C89: Effect of Sec. Deposit/Maint.Deposit/Power Deposit | F89: ='Security Deposit'!C17 -> 10.7299 | G89: =F89*F6 -> 115.49665 | I89: =F89/$J$5 -> 0.10217006 | J89: =I89*I6 -> 1.0997586
B90: =+B89+1 -> 5 | C90: CAM-IFRS16 | F90: =+F64 -> 17.548935 | G90: =+F90*$F$6 -> 188.89674 | I90: =F90/$J$5 -> 0.16710089 | J90: =I90*I6 -> 1.7986739
B91: =+B89+1 -> 5 | C91: Effect Lease acquisition (Brokerage) | F91: =(+F83/F21/F54) -> 0 | G91: =(+G83/G21/G54) -> 0 | I91: =F91/$J$5 -> 0 | J91: =+I91*$I$6 -> 0
B92: =+B91+1 -> 6 | C92: Effect of Stamp Duty & registration | F92: =F82/F21/F54 -> 0.82518144 | G92: =G82/G21/G54 -> 8.882253 | I92: =+F92/J5 -> 0.0078573742 | J92: =+I92*$I$6 -> 0.084576776
B93: =+B92+1 -> 7 | C93: Property Management Fees | F93: =+G93/F6 -> 21.95751 | G93: =(+SUM(G86:G92)+G103)*7% -> 236.35064 | I93: =+F93/J5 -> 0.20907932 | J93: =I93*I6 -> 2.2505298
B94: =+B93+1 -> 8 | C94: Net Rent I | F94: =SUM(F86:F93) -> 199.26804 | G94: =SUM(G86:G93) -> 2144.9212 | I94: =SUM(I86:I93) -> 1.8974295 | J94: =SUM(J86:J93) -> 20.423931
B96: Net Rent II - Refinancing Cost | F96: Per sq. ft | G96: Per sq. Mtr | I96: Per sq. ft | J96: Per sq. Mtr
B97: 1 | C97: =+C76 -> Siemens Standard Fitout (Existing) | F97: 0 | G97: =+F97*F6 -> 0 | I97: =F97/J5 -> 0 | J97: =+I97*I6 -> 0
B98: =+B97+1 -> 2 | C98: =+C77 -> Siemens Standard Fitout (New) | F98: ='CAPEX and PM'!B29 -> 57.834864 | G98: =+F98*F6 -> 622.53447 | I98: =+F98/$J$5 -> 0.55070333 | J98: =+I98*$I$6 -> 5.9277706
B99: =+B98+1 -> 3 | C99: =+C78 -> Capex over the period of lease period | F99: ='CAPEX and PM'!B98 -> 73.736885 | G99: =+F99*F6 -> 793.70383 | I99: =+F99/$J$5 -> 0.70212231 | J99: =+I99*$I$6 -> 7.5576445
B100: =+B99+1 -> 4 | C100: =+C79 -> PM cost over the period of lease period | F100: =+'CAPEX and PM'!B105 -> 3.6492089 | G100: =+F100*F6 -> 39.280084 | I100: =+F100/$J$5 -> 0.034747751 | J100: =+I100*$I$6 -> 0.3740248
B101: =+B100+1 -> 5 | C101: =+C80 -> Asset Retirement Obligation ( Removal & Restoration Obligation) | F101: ='Security Deposit'!D25 -> 1.1472222 | G101: =F101*10.764 -> 12.3487 | I101: =+F101/J5 -> 0.010923845 | J101: =+G101/J5 -> 0.11758427
B102: =+B101+1 -> 6 | C102: Passive Data Network | F102: =+F81/F21/F27 -> 0 | G102: =+F102*F6 -> 0 | I102: =+F102/J5 -> 0 | J102: =+I102*I6 -> 0
B103: =+B102+1 -> 7 | C103: Net Rent II | F103: =SUM(F97:F102) -> 136.36818 | G103: =SUM(G97:G102) -> 1467.8671 | I103: =SUM(I97:I102) -> 1.2984972 | J103: =SUM(J97:J102) -> 13.977024
B105: Net Rent I & II | F105: Per sq. ft | G105: Per sq. Mtr | I105: Per sq. ft | J105: Per sq. Mtr
B106: 1 | C106: Net Rent I | F106: =+F94 -> 199.26804 | G106: =+G94 -> 2144.9212 | I106: =+I94 -> 1.8974295 | J106: =+J94 -> 20.423931
B107: =+B106+1 -> 2 | C107: Net Rent II | F107: =+F103 -> 136.36818 | G107: =+G103 -> 1467.8671 | I107: =+I103 -> 1.2984972 | J107: =+J103 -> 13.977024
...

Sheet Lease Size
A5: RENTAL CALCULATION FOR NEW LEASE
A7: Lease Size Calculation for 3 Years
A8: Cash Outflow for the period | P8: Net Present Value Calculation
A9: =+'Rent Calculation'!B1 -> 0 | B9: Net rent (INR) | C9: Terrace Rent (INR) | D9: Rent Signages (INR) | E9: Car Park (INR) | F9: Common area maintenance (INR) | G9: Total nominal (INR) A | H9: Total (Euro) | I9: Capex in Coming years (INR) B | J9: PM in Coming years (INR) C | K9: Total nominal (INR) A + B + C | L9: Total (Euro) | M9: Net Present outflow (Discounted ) (INR) | N9: Net Present outflow (Discounted ) (€) | P9: WACC | Q9: =+'Rent Calculation'!F28 -> 0.105 | S9: Ex. Rate | T9: ='Rent Calculation'!J5 -> 105.02
A10: per/sq.ft./month | B10: =+'Rent Calculation'!F39 -> 120 | D10: =(+'Rent Calculation'!F210*114.5%)/'Rent Calculation'!F21/12 -> 0 | E10: =+((+'Rent Calculation'!F43*'Rent Calculation'!F44)/'Rent Calculation'!F23) -> 12.611666 | F10: =+'Rent Calculation'!F41 -> 15.48 | G10: =SUM(B10:F10) -> 148.09167
A11: per month | B11: =+B10*'Rent Calculation'!F21 -> 1141800 | D11: =+D10*'Rent Calculation'!F21 -> 0 | E11: =+E10*'Rent Calculation'!F21 -> 120000 | F11: =F10*'Rent Calculation'!F21 -> 147292.2 | G11: =SUM(B11:F11) -> 1409092.2 | Q11: Year 1 | R11: Year 2 | S11: Year 3 | T11: Year 4 | U11: Year 5 | V11: Year 6 | W11: Year 7 | X11: Year 8 | Y11: Year 9 | Z11: Year 10 | AA11: Total
A12: rent per year 1st year | B12: =+'Rent Calculation'!C210 -> 9134400 | D12: =+D11*6 -> 0 | E12: =+'Rent Calculation'!G210 -> 1360000 | F12: =+'Rent Calculation'!I210 -> 1178337.6 | G12: =SUM(B12:F12) -> 11672738 | H12: =G12/$T$9 -> 111147.76 | I12: =+Q28 -> 14000000 | J12: =+Q27 -> 1500000 | K12: =+G12+I12+J12 -> 27172738 | L12: =+K12/$T$9 -> 258738.69
A13: rent per year 2nd year | B13: =+'Rent Calculation'!C211 -> 13701600 | D13: =+D11*12 -> 0 | E13: =+'Rent Calculation'!G211 -> 2040000 | F13: =+'Rent Calculation'!I211 -> 1826423.3 | G13: =SUM(B13:F13) -> 17568023 | H13: =G13/$T$9 -> 167282.64 | I13: =+R28 -> 12000000 | J13: =+R27 -> 200000 | K13: =+G13+I13+J13 -> 29768023 | L13: =+K13/$T$9 -> 283450.99 | Q13: (€) | R13: (€) | S13: (€) | T13: (€) | U13: (€) | V13: (€) | W13: (€) | X13: (€) | Y13: (€) | Z13: (€) | AA13: (€)
A14: rent per year 3rd year | B14: =+'Rent Calculation'!C212 -> 13701600 | D14: =+D13 -> 0 | E14: =+'Rent Calculation'!G212 -> 2040000 | F14: =+'Rent Calculation'!I212 -> 1917744.4 | G14: =SUM(B14:F14) -> 17659344 | H14: =G14/$T$9 -> 168152.2 | I14: =+S28 -> 5000000 | J14: =+S27 -> 200000 | K14: =+G14+I14+J14 -> 22859344 | L14: =+K14/$T$9 -> 217666.58 | P14: Rent, CAM, Car Park, Payment | Q14: =+H12 -> 111147.76 | R14: =H13 -> 167282.64 | S14: =H14 -> 168152.2 | T14: =H15 -> 184054.39 | U14: =+H16 -> 192507.65 | V14: =+H17 -> 193514.27 | W14: =+H18 -> 64618.409 | X14: =+H19 -> 0 | Y14: =H20 -> 0 | Z14: =H21 -> 0 | AA14: =SUM(Q14:Z14) -> 1081277.3
A15: rent per year 4th year | B15: =+'Rent Calculation'!C213 -> 15071760 | D15: =+D12+(D12*115%) -> 0 | E15: =+'Rent Calculation'!G213 -> 2244000 | F15: =+'Rent Calculation'!I213 -> 2013631.7 | G15: =SUM(B15:F15) -> 19329392 | H15: =G15/$T$9 -> 184054.39 | I15: =+T28 -> 6000000 | J15: =+T27 -> 200000 | K15: =+G15+I15+J15 -> 25529392 | L15: =+K15/$T$9 -> 243090.76 | P15: Security Deposit | Q15: =+Q26/$T$9 -> 113483.15 | R15: =+R26/$T$9 -> 0 | S15: =+S26/$T$9 -> 0 | T15: =+T26/$T$9 -> 0 | U15: =+U26/$T$9 -> 0 | V15: =+V26/$T$9 -> 0 | W15: =+W26/$T$9 -> -113483.15 | X15: =+X26/$T$9 -> 0 | ... Z15: =+Z26/$T$9 -> 0 | AA15: =SUM(Q15:Z15) -> 0
A16: rent per year 5th year | B16: =+'Rent Calculation'!C214 -> 15756840 | D16: =+D13*115% -> 0 | E16: =+'Rent Calculation'!G214 -> 2346000 | F16: =+'Rent Calculation'!I214 -> 2114313.2 | G16: =SUM(B16:F16) -> 20217153 | H16: =G16/$T$9 -> 192507.65 | I16: =+U28 -> 6000000 | J16: =+U27 -> 200000 | K16: =+G16+I16+J16 -> 26417153 | L16: =+K16/$T$9 -> 251544.02 | P16: Project Maintenace | Q16: =+Q27/$T$9 -> 14282.994 | R16: =+R27/$T$9 -> 1904.3992 | S16: =+S27/$T$9 -> 1904.3992 | T16: =+T27/$T$9 -> 1904.3992 | U16: =+U27/$T$9 -> 1904.3992 | V16: =+V27/$T$9 -> 1904.3992 | W16: =+W27/$T$9 -> 0 | X16: =+X27/$T$9 -> 0 | ... Z16: =+Z27/$T$9 -> 0 | AA16: =SUM(Q16:Z16) -> 23804.99
A17: rent per year 6th year | B17: =+'Rent Calculation'!C215 -> 15756840 | D17: =+D16 -> 0 | E17: =+'Rent Calculation'!G215 -> 2346000 | F17: =+'Rent Calculation'!I215 -> 2220028.9 | G17: =SUM(B17:F17) -> 20322869 | H17: =G17/$T$9 -> 193514.27 | I17: =+V28 -> 0 | J17: =+V27 -> 200000 | K17: =+G17+I17+J17 -> 20522869 | L17: =+K17/$T$9 -> 195418.67 | P17: Capex | Q17: =+Q28/$T$9 -> 133307.94 | R17: =+R28/$T$9 -> 114263.95 | S17: =+S28/$T$9 -> 47609.979 | T17: =+T28/$T$9 -> 57131.975 | U17: =+U28/$T$9 -> 57131.975 | V17: =+V28/$T$9 -> 0 | W17: =+W28/$T$9 -> 0 | X17: =+X28/$T$9 -> 0 | ... Z17: =+Z28/$T$9 -> 0 | AA17: =SUM(Q17:Z17) -> 409445.82
A18: rent per year 7th year | B18: =+'Rent Calculation'!C216 -> 5252280 | D18: =(+D17/2)+(D17/2*115%) -> 0 | E18: =+'Rent Calculation'!G216 -> 782000 | F18: =+'Rent Calculation'!I216 -> 751945.28 | G18: =SUM(B18:F18) -> 6786225.3 | H18: =G18/$T$9 -> 64618.409 | I18: =+W28 -> 0 | J18: =+W27 -> 0 | K18: =+G18+I18+J18 -> 6786225.3 | L18: =+K18/$T$9 -> 64618.409 | AA18: =SUM(Q18:Z18) -> 0
A19: rent per year 8th year | B19: =+'Rent Calculation'!C217 -> 0 | D19: =+D17*115% -> 0 | E19: =+'Rent Calculation'!G217 -> 0 | F19: =+'Rent Calculation'!I217 -> 0 | G19: =SUM(B19:F19) -> 0 | H19: =G19/$T$9 -> 0 | I19: =+X28 -> 0 | J19: =+X27 -> 0 | K19: =+G19+I19+J19 -> 0 | L19: =+K19/$T$9 -> 0
A20: rent per year 9th year | B20: =+'Rent Calculation'!C218 -> 0 | D20: =D19 -> 0 | E20: =+'Rent Calculation'!G218 -> 0 | F20: =+'Rent Calculation'!I218 -> 0 | G20: =SUM(B20:F20) -> 0 | H20: =G20/$T$9 -> 0 | I20: =+Y28 -> 0 | J20: =+Y27 -> 0 | K20: =+G20+I20+J20 -> 0 | L20: =+K20/$T$9 -> 0
A21: rent per year 10th year | B21: =+'Rent Calculation'!C219 -> 0 | D21: =+D20/2 -> 0 | E21: =+'Rent Calculation'!G219 -> 0 | F21: =(+'Rent Calculation'!I219)*114.5% -> 0 | G21: =SUM(B21:F21) -> 0 | H21: =G21/$T$9 -> 0 | I21: =+Z28 -> 0 | J21: =+Z27 -> 0 | K21: =+G21+I21+J21 -> 0 | L21: =+K21/$T$9 -> 0
P22: Total Cash Outflow for the period | Q22: =SUM(Q14:Q20) -> 372221.84 | R22: =SUM(R14:R20) -> 283450.99 | S22: =SUM(S14:S20) -> 217666.58 | T22: =SUM(T14:T20) -> 243090.76 | U22: =SUM(U14:U20) -> 251544.02 | V22: =SUM(V14:V20) -> 195418.67 | W22: =SUM(W14:W20) -> -48864.737 | X22: =SUM(X14:X20) -> 0 | ... AA22: =SUM(AA14:AA20) -> 1514528.1
A23: Total rent for the period | B23: =SUM(B12:B22) -> 88375320 | C23: =SUM(C12:C22) -> 0 | D23: =SUM(D12:D22) -> 0 | E23: =SUM(E12:E22) -> 13158000 | F23: =SUM(F12:F22) -> 12022424 | G23: =SUM(G12:G22) -> 1.1355574e+08 | H23: =SUM(H12:H22) -> 1081277.3 | I23: =SUM(I12:I22) -> 43000000 | ... L23: =SUM(L12:L22) -> 1514528.1 | M23: =+N23*$T$9 -> 1.1857943e+08 | N23: =+R34 -> 1129112.9 | Q23: =Q22/1.105 -> 336852.34 | R23: =R22/1.105^2 -> 232141.84 | S23: =S22/1.105^3 -> 161326.21 | T23: =T22/1.105^4 -> 163049.45 | U23: =U22/1.105^5 -> 152687.19
Q24: (INR) | R24: (INR) | S24: (INR) | T24: (INR) | U24: (INR) | V24: (INR) | W24: (INR) | X24: (INR) | Y24: (INR) | Z24: (INR) | AA24: Total
A25: Lease Acquisition cost | G25: =+'Rent Calculation'!G194+'Rent Calculation'!F30 -> 565315.3 | H25: =G25/$T$9 -> 5382.9299 | K25: =+G25+I25+J25 -> 565315.3 | P25: Rent, CAM, Car Park, Payment | Q25: =+G12 -> 11672738 | R25: =+R14*$T$9 -> 17568023 | S25: =+S14*$T$9 -> 17659344 | T25: =+T14*$T$9 -> 19329392 | U25: =+U14*$T$9 -> 20217153 | V25: =+V14*$T$9 -> 20322869 | W25: =+W14*$T$9 -> 6786225.3 | X25: =+X14*$T$9 -> 0 | Y25: =+Y14*$T$9 -> 0 | Z25: =+Z14*$T$9 -> 0 | AA25: =SUM(Q25:Z25) -> 1.1355574e+08
A26: Fitout Cost | G26: ='CAPEX and PM'!B3 -> 34000000 | H26: =G26/$T$9 -> 323747.86 | K26: =+G26+I26+J26 -> 34000000 | P26: Security Deposit | Q26: =U34 -> 11918000 | W26: =-Q26 -> -11918000 | Z26: 0 | AA26: =SUM(Q26:Z26) -> 0
P27: Project Maintenace | Q27: ='CAPEX and PM'!F104 -> 1500000 | R27: ='CAPEX and PM'!G104 -> 200000 | S27: ='CAPEX and PM'!H104 -> 200000 | T27: ='CAPEX and PM'!I104 -> 200000 | U27: ='CAPEX and PM'!J104 -> 200000 | V27: =+'CAPEX and PM'!K104 -> 200000 | W27: =+'CAPEX and PM'!L104 -> 0 | X27: =+'CAPEX and PM'!M104 -> 0 | Y27: =+'CAPEX and PM'!N104 -> 0 | Z27: =+'CAPEX and PM'!O104 -> 0 | AA27: =SUM(Q27:Z27) -> 2500000
A28: Total one time Cost | G28: =SUM(G25:G27) -> 34565315 | H28: =SUM(H25:H27) -> 329130.79 | I28: =SUM(I25:I27) -> 0 | K28: =SUM(K25:K27) -> 34565315 | M28: =+N28*T9 -> 34565315 | N28: =+H28 -> 329130.79 | P28: Capex | Q28: =+'CAPEX and PM'!F38 -> 14000000 | R28: =+'CAPEX and PM'!G38 -> 12000000 | S28: =+'CAPEX and PM'!H38 -> 5000000 | T28: =+'CAPEX and PM'!I38 -> 6000000 | U28: =+'CAPEX and PM'!J38 -> 6000000 | V28: =+'CAPEX and PM'!K38 -> 0 | W28: =+'CAPEX and PM'!L38 -> 0 | X28: =+'CAPEX and PM'!M38 -> 0 | ... Z28: =+'CAPEX and PM'!O38 -> 0 | AA28: =SUM(Q28:Z28) -> 43000000
P30: Total Cash Outflow for the period | Q30: =SUM(Q25:Q29) -> 39090738 | R30: =SUM(R25:R29) -> 29768023 | S30: =SUM(S25:S29) -> 22859344 | T30: =SUM(T25:T29) -> 25529392 | U30: =SUM(U25:U29) -> 26417153 | V30: =SUM(V25:V29) -> 20522869 | W30: =SUM(W25:W29) -> -5131774.7 | X30: =SUM(X25:X29) -> 0 | ... AA30: =SUM(AA25:AA29) -> 1.5905574e+08
A31: Total Cash Outflow for the period | G31: =+K23+G28 -> 1.9362106e+08 | H31: =+L23+H28 -> 1843658.9 | M31: =+M23+M28 -> 1.5314475e+08 | N31: =N23+N28 -> 1458243.6
A32: Lease Size in mn | H32: =+H31/1000000 -> 1.8436589 | N32: =+N31/1000000 -> 1.4582436 | Q32: (INR) | R32: (Euro) | T32: Security Deposit Details
U33: (INR) | V33: (Euro)
A34: Investment IT | P34: Net Present Value | Q34: =+NPV(Q9,Q30,R30,S30,T30,U30,V30,W30,X30,Y30,Z30) -> 1.1857943e+08 | R34: =+NPV(Q9,Q22:Z22) -> 1129112.9 | T34: Security Deposit-A | U34: =('Rent Calculation'!F67+'Rent Calculation'!F71+'Rent Calculation'!F69) -> 11918000 | V34: =+U34/$T$9 -> 113483.15
T35: Fitout Deposit | U35: 0 | V35: =+U35/$T$9 -> 0
A36: Total Project Cost | H36: =+H32+H34 -> 1.8436589 | N36: =+N32+N34 -> 1.4582436 | T36: Maintenance Deposit-B | U36: 0 | V36: =+U36/$T$9 -> 0
T37: Power Deposit-C | U37: =+'Rent Calculation'!F72 -> 0 | V37: =+U37/$T$9 -> 0
T38: Total | U38: =SUM(U34:U37) -> 11918000 | V38: =SUM(V34:V37) -> 113483.15

Sheet Lease Rent
B1: Rental terms as per agreement | K1: 10.764 | L1: =D24 -> 130
B2: From | C2: To | D2: Months | E2: Area in SQF | F2: Area in SQM | G2: Escalation | H2: Rental | I2: Car Parks per # | J2: CAM | K2: Rental SQM | L2: Car Parks SQM | M2: CAM SQM | N2: Rent+Car Parks | P2: FY | Q2: Rent | R2: Car Park | S2: CAM | T2: Total
B3: 45976 | C3: 46295 | D3: =ROUND((C3-B3)/30,0)-0.5 -> 10.5 | E3: ='Rent Calculation'!F21 -> 9515 | F3: ='Rent Calculation'!G21 -> 883.96507 | H3: ='Rent Calculation'!F36 -> 120 | I3: =E25 -> 1307.6923 | J3: =14.67723796875 -> 14.677238 | K3: =H3*$K$1 -> 1291.68 | L3: =I3/E3 -> 0.13743482 | M3: =J3*$K$1 -> 157.98579 | N3: =K3+L3 -> 1291.8174 | P3: =YEAR(C3) -> 2026 | Q3: =D3*E3*H3 -> 11988900 | R3: =$I$37*D3 -> 1785000 | S3: =D3*E3*J3 -> 1466366.2 | T3: =SUM(Q3:S3) -> 15240266 | U3: =T3/12 -> 1270022.2
B4: =C3+1 -> 46296 | C4: 46340 | D4: =ROUND((C4-B4)/30,0)+0.5 -> 1.5 | E4: =E3 -> 9515 | F4: =F3 -> 883.96507 | H4: =H3 -> 120 | I4: =I3 -> 1307.6923 | J4: =J3 -> 14.677238 | K4: =H4*$K$1 -> 1291.68 | L4: =I4/E4 -> 0.13743482 | M4: =J4*$K$1 -> 157.98579 | N4: =K4+L4 -> 1291.8174 | P4: =P3+1 -> 2027 | Q4: =D4*E4*H4 -> 1712700 | R4: =$I$37*D4 -> 255000 | S4: =D4*E4*J4 -> 209480.88 | T4: =SUM(Q4:S4) -> 2177180.9
B5: =C4+1 -> 46341 | C5: 46660 | D5: =ROUND((C5-B5)/30,0)-0.5 -> 10.5 | E5: =E4 -> 9515 | F5: =F4 -> 883.96507 | H5: =H3 -> 120 | I5: =I3 -> 1307.6923 | J5: =J4*1.05 -> 15.4111 | K5: =H5*$K$1 -> 1291.68 | L5: =I5/E5 -> 0.13743482 | M5: =J5*$K$1 -> 165.88508 | N5: =K5+L5 -> 1291.8174 | P5: =P4 -> 2027 | Q5: =D5*E5*H5 -> 11988900 | R5: =$I$37*D5 -> 1785000 | S5: =D5*E5*J5 -> 1539684.5 | T5: =SUM(Q5:S5) -> 15313584
B6: =C5+1 -> 46661 | C6: 46705 | D6: =ROUND((C6-B6)/30,0)+0.5 -> 1.5 | E6: =E5 -> 9515 | F6: =F5 -> 883.96507 | H6: =H4 -> 120 | I6: =I4 -> 1307.6923 | J6: =J5 -> 15.4111 | K6: =H6*$K$1 -> 1291.68 | L6: =I6/E6 -> 0.13743482 | M6: =J6*$K$1 -> 165.88508 | N6: =K6+L6 -> 1291.8174 | P6: =P5+1 -> 2028 | Q6: =D6*E6*H6 -> 1712700 | R6: =$I$37*D6 -> 255000 | S6: =D6*E6*J6 -> 219954.92 | T6: =SUM(Q6:S6) -> 2187654.9
B7: =C6+1 -> 46706 | C7: 47026 | D7: =ROUND((C7-B7)/30,0)-0.5 -> 10.5 | E7: =E6 -> 9515 | F7: =F6 -> 883.96507 | H7: =H5 -> 120 | I7: =I5 -> 1307.6923 | J7: =J6*1.05 -> 16.181655 | K7: =H7*$K$1 -> 1291.68 | L7: =I7/E7 -> 0.13743482 | M7: =J7*$K$1 -> 174.17933 | N7: =K7+L7 -> 1291.8174 | P7: =P6 -> 2028 | Q7: =D7*E7*H7 -> 11988900 | R7: =$I$37*D7 -> 1785000 | S7: =D7*E7*J7 -> 1616668.7 | T7: =SUM(Q7:S7) -> 15390569
B8: =C7+1 -> 47027 | C8: 47071 | D8: =ROUND((C8-B8)/30,0)+0.5 -> 1.5 | E8: =E7 -> 9515 | F8: =F7 -> 883.96507 | H8: =H6+(H6*G8) -> 120 | I8: =I6+(I6*G8) -> 1307.6923 | J8: =J7 -> 16.181655 | K8: =H8*$K$1 -> 1291.68 | L8: =I8/E8 -> 0.13743482 | M8: =J8*$K$1 -> 174.17933 | N8: =K8+L8 -> 1291.8174 | P8: =P7+1 -> 2029 | Q8: =D8*E8*H8 -> 1712700 | R8: =$I$37*D8 -> 255000 | S8: =D8*E8*J8 -> 230952.67 | T8: =SUM(Q8:S8) -> 2198652.7
E9: =E8 -> 9515 | F9: =F8 -> 883.96507 | H9: =H7+(H7*G9) -> 120 | I9: =I7+(I7*G9) -> 1307.6923 | J9: =J8 -> 16.181655 | K9: =H9*$K$1 -> 1291.68 | L9: =I9/E9 -> 0.13743482 | M9: =J9*$K$1 -> 174.17933 | N9: =K9+L9 -> 1291.8174 | P9: =P8 -> 2029 | Q9: =D9*E9*H9 -> 0 | R9: =D9*$D$24*I9 -> 0 | S9: =D9*E9*J9 -> 0 | T9: =SUM(Q9:S9) -> 0
E10: =E9 -> 9515 | F10: =F9 -> 883.96507 | H10: =H8+(H8*G10) -> 120 | I10: =I8+(I8*G10) -> 1307.6923 | J10: =J9 -> 16.181655 | K10: =H10*$K$1 -> 1291.68 | L10: =I10/E10 -> 0.13743482 | M10: =J10*$K$1 -> 174.17933 | N10: =K10+L10 -> 1291.8174 | P10: =P9+1 -> 2030 | Q10: =D10*E10*H10 -> 0 | R10: =D10*$D$24*I10 -> 0 | S10: =D10*E10*J10 -> 0 | T10: =SUM(Q10:S10) -> 0
B11: Total | D11: 42 | P11: Total | Q11: =SUM(Q3:Q10) -> 41104800 | R11: =SUM(R3:R10) -> 6120000 | S11: =SUM(S3:S10) -> 5283107.8 | T11: =SUM(T3:T10) -> 52507908
G17: Rentals
G18: Year | H18: Months | I18: Rentals | J18: CAM | K18: Total
G19: 2026 | H19: =SUMIF($A$31:$A$1048576,$G19,$D$31:$D$102) -> 8 | I19: =SUMIF($A$31:$A$1048576,$G19,$K$31:$K$102) -> 9134400 | J19: =SUMIF($A$31:$A$1048576,$G19,$L$31:$L$102) -> 1178337.6 | K19: =I19+J19 -> 10312738
G20: =G19+1 -> 2027 | H20: =SUMIF($A$31:$A$1048576,$G20,$D$31:$D$102) -> 12 | I20: =SUMIF($A$31:$A$1048576,$G20,$K$31:$K$102) -> 13701600 | J20: =SUMIF($A$31:$A$1048576,$G20,$L$31:$L$102) -> 1826423.3 | K20: =I20+J20 -> 15528023
B21: Car parks | C21: Rates | D21: No of Vehicles | E21: Amount | G21: =G20+1 -> 2028 | H21: =SUMIF($A$31:$A$1048576,$G21,$D$31:$D$102) -> 12 | I21: =SUMIF($A$31:$A$1048576,$G21,$K$31:$K$102) -> 13701600 | J21: =SUMIF($A$31:$A$1048576,$G21,$L$31:$L$102) -> 1917744.4 | K21: =I21+J21 -> 15619344
B22: 4 Wheeler | C22: 1500 | D22: 80 | E22: =C22*D22 -> 120000 | G22: =G21+1 -> 2029 | H22: =SUMIF($A$31:$A$1048576,$G22,$D$31:$D$102) -> 12 | I22: =SUMIF($A$31:$A$1048576,$G22,$K$31:$K$102) -> 15071760 | J22: =SUMIF($A$31:$A$1048576,$G22,$L$31:$L$102) -> 2013631.7 | K22: =I22+J22 -> 17085392
B23: 2 Wheeler | C23: 1000 | D23: 50 | E23: =C23*D23 -> 50000 | G23: =G22+1 -> 2030 | H23: =SUMIF($A$31:$A$1048576,$G23,$D$31:$D$102) -> 12 | I23: =SUMIF($A$31:$A$1048576,$G23,$K$31:$K$102) -> 15756840 | J23: =SUMIF($A$31:$A$1048576,$G23,$L$31:$L$102) -> 2114313.2 | K23: =I23+J23 -> 17871153
B24: Total | D24: =D22+D23 -> 130 | E24: =E22+E23 -> 170000 | G24: =G23+1 -> 2031 | H24: =SUMIF($A$31:$A$1048576,$G24,$D$31:$D$102) -> 12 | I24: =SUMIF($A$31:$A$1048576,$G24,$K$31:$K$102) -> 15756840 | J24: =SUMIF($A$31:$A$1048576,$G24,$L$31:$L$102) -> 2220028.9 | K24: =I24+J24 -> 17976869
E25: =IFERROR(E24/D24,0) -> 1307.6923 | G25: =G24+1 -> 2032 | H25: =SUMIF($A$31:$A$1048576,$G25,$D$31:$D$102) -> 4 | I25: =SUMIF($A$31:$A$1048576,$G25,$K$31:$K$102) -> 5252280 | J25: =SUMIF($A$31:$A$1048576,$G25,$L$31:$L$102) -> 751945.28 | K25: =I25+J25 -> 6004225.3
H26: =SUM(H19:H25) -> 72 | I26: =SUM(I19:I25) -> 88375320 | J26: =SUM(J19:J25) -> 12022424 | K26: =SUM(K19:K25) -> 1.0039774e+08
A30: Year | B30: From | C30: To | D30: Months | E30: Area in SQF | F30: Area in SQM | G30: Escalation | H30: Rental | I30: Car Parks per # | J30: CAM | K30: Rental SQF | L30: CAM SQF | M30: Total | N30: Rentals | O30: CAM | P30: PARKING
A31: 2026 | B31: 46023 | C31: =B31+30 -> 46053 | D31: 1 | E31: ='Rent Calculation'!$F$23 -> 9515 | F31: ='Rent Calculation'!G23 -> 883.96507 | H31: =Main!B7 -> 120 | I31: =E24 -> 170000 | J31: =15.48 -> 15.48 | K31: =H31*E31 -> 1141800 | L31: =J31*E31 -> 147292.2 | M31: =I31+K31+L31 -> 1459092.2
A32: =A31 -> 2026 | B32: =C31+1 -> 46054 | C32: =B32+30-3 -> 46081 | D32: 1 | E32: 9515 | F32: 883.96507 | H32: =H31 -> 120 | I32: =I31 -> 170000 | J32: 15.48 | K32: =H32*E32 -> 1141800 | L32: =J32*E32 -> 147292.2 | M32: =I32+K32+L32 -> 1459092.2
A33: =A32 -> 2026 | B33: =C32+1 -> 46082 | C33: =B33+30 -> 46112 | D33: 1 | E33: =E32 -> 9515 | F33: =F32 -> 883.96507 | H33: =H32 -> 120 | I33: =I32 -> 170000 | J33: =J32 -> 15.48 | K33: =H33*E33 -> 1141800 | L33: =J33*E33 -> 147292.2 | M33: =I33+K33+L33 -> 1459092.2
A34: =A33 -> 2026 | B34: =C33+1 -> 46113 | C34: =B34+30-1 -> 46142 | D34: 1 | E34: =E33 -> 9515 | F34: =F33 -> 883.96507 | H34: =H33 -> 120 | I34: =I33 -> 170000 | J34: =J33 -> 15.48 | K34: =H34*E34 -> 1141800 | L34: =J34*E34 -> 147292.2 | M34: =I34+K34+L34 -> 1459092.2
A35: =A34 -> 2026 | B35: =C34+1 -> 46143 | C35: =B35+30 -> 46173 | D35: 1 | E35: =E34 -> 9515 | F35: =F34 -> 883.96507 | H35: =H34 -> 120 | I35: =I34 -> 170000 | J35: =J34 -> 15.48 | K35: =H35*E35 -> 1141800 | L35: =J35*E35 -> 147292.2 | M35: =I35+K35+L35 -> 1459092.2
A36: =A35 -> 2026 | B36: =C35+1 -> 46174 | C36: =B36+30-1 -> 46203 | D36: 1 | E36: =E35 -> 9515 | F36: =F35 -> 883.96507 | H36: =H35 -> 120 | I36: =I35 -> 170000 | J36: =J35 -> 15.48 | K36: =H36*E36 -> 1141800 | L36: =J36*E36 -> 147292.2 | M36: =I36+K36+L36 -> 1459092.2
A37: =A36 -> 2026 | B37: =C36+1 -> 46204 | C37: =B37+30-1 -> 46233 | D37: 1 | E37: =E36 -> 9515 | F37: =F36 -> 883.96507 | H37: =H36 -> 120 | I37: =I36 -> 170000 | J37: =J36 -> 15.48 | K37: =H37*E37 -> 1141800 | L37: =J37*E37 -> 147292.2 | M37: =I37+K37+L37 -> 1459092.2
A38: =A37 -> 2026 | B38: =C37+1 -> 46234 | C38: =B38+30 -> 46264 | D38: 1 | E38: =E37 -> 9515 | F38: =F37 -> 883.96507 | H38: =H37 -> 120 | I38: =I37 -> 170000 | J38: =J37 -> 15.48 | K38: =H38*E38 -> 1141800 | L38: =J38*E38 -> 147292.2 | M38: =I38+K38+L38 -> 1459092.2
A39: =A38+1 -> 2027 | B39: =C38+1 -> 46265 | C39: =B39+30 -> 46295 | D39: 1 | E39: =E38 -> 9515 | F39: =F38 -> 883.96507 | H39: =H38 -> 120 | I39: =I38 -> 170000 | J39: =J38 -> 15.48 | K39: =H39*E39 -> 1141800 | L39: =J39*E39 -> 147292.2 | M39: =I39+K39+L39 -> 1459092.2 | N39: =SUM(K31:K38) -> 9134400 | O39: =SUM(L31:L38) -> 1178337.6 | P39: =SUM(I31:I38) -> 1360000
A40: =A39 -> 2027 | B40: =C39+1 -> 46296 | C40: =B40+30 -> 46326 | D40: 1 | E40: =E39 -> 9515 | F40: =F39 -> 883.96507 | H40: =H39 -> 120 | I40: =I39 -> 170000 | J40: =J39 -> 15.48 | K40: =H40*E40 -> 1141800 | L40: =J40*E40 -> 147292.2 | M40: =I40+K40+L40 -> 1459092.2
A41: =A40 -> 2027 | B41: =C40+1 -> 46327 | C41: =B41+30-1 -> 46356 | D41: 1 | E41: =E40 -> 9515 | F41: =F40 -> 883.96507 | H41: =H40 -> 120 | I41: =I40 -> 170000 | J41: =J40 -> 15.48 | K41: =H41*E41 -> 1141800 | L41: =J41*E41 -> 147292.2 | M41: =I41+K41+L41 -> 1459092.2
A42: =A41 -> 2027 | B42: =C41+1 -> 46357 | C42: =B42+30 -> 46387 | D42: 1 | E42: =E41 -> 9515 | F42: =F41 -> 883.96507 | H42: =H41 -> 120 | I42: =I41 -> 170000 | J42: =J41 -> 15.48 | K42: =H42*E42 -> 1141800 | L42: =J42*E42 -> 147292.2 | M42: =I42+K42+L42 -> 1459092.2
A43: =A42 -> 2027 | B43: =C42+1 -> 46388 | C43: =B43+30 -> 46418 | D43: 1 | E43: =E42 -> 9515 | F43: =F42 -> 883.96507 | H43: =H42 -> 120 | I43: =I42 -> 170000 | J43: =J42*1.05 -> 16.254 | K43: =H43*E43 -> 1141800 | L43: =J43*E43 -> 154656.81 | M43: =I43+K43+L43 -> 1466456.8
A44: =A43 -> 2027 | B44: =C43+1 -> 46419 | C44: =B44+30-3 -> 46446 | D44: 1 | E44: =E43 -> 9515 | F44: =F43 -> 883.96507 | H44: =H43 -> 120 | I44: =I43 -> 170000 | J44: =J43 -> 16.254 | K44: =H44*E44 -> 1141800 | L44: =J44*E44 -> 154656.81 | M44: =I44+K44+L44 -> 1466456.8
A45: =A44 -> 2027 | B45: =C44+1 -> 46447 | C45: =B45+30 -> 46477 | D45: 1 | E45: =E44 -> 9515 | F45: =F44 -> 883.96507 | H45: =H44 -> 120 | I45: =I44 -> 170000 | J45: =J44 -> 16.254 | K45: =H45*E45 -> 1141800 | L45: =J45*E45 -> 154656.81 | M45: =I45+K45+L45 -> 1466456.8
A46: =A45 -> 2027 | B46: =C45+1 -> 46478 | C46: =B46+30-1 -> 46507 | D46: 1 | E46: =E45 -> 9515 | F46: =F45 -> 883.96507 | H46: =H45 -> 120 | I46: =I45 -> 170000 | J46: =J45 -> 16.254 | K46: =H46*E46 -> 1141800 | L46: =J46*E46 -> 154656.81 | M46: =I46+K46+L46 -> 1466456.8
A47: =A46 -> 2027 | B47: =C46+1 -> 46508 | C47: =B47+30 -> 46538 | D47: 1 | E47: =E46 -> 9515 | F47: =F46 -> 883.96507 | H47: =H46 -> 120 | I47: =I46 -> 170000 | J47: =J46 -> 16.254 | K47: =H47*E47 -> 1141800 | L47: =J47*E47 -> 154656.81 | M47: =I47+K47+L47 -> 1466456.8
A48: =A47 -> 2027 | B48: =C47+1 -> 46539 | C48: =B48+30-1 -> 46568 | D48: 1 | E48: =E47 -> 9515 | F48: =F47 -> 883.96507 | H48: =H47 -> 120 | I48: =I47 -> 170000 | J48: =J47 -> 16.254 | K48: =H48*E48 -> 1141800 | L48: =J48*E48 -> 154656.81 | M48: =I48+K48+L48 -> 1466456.8
A49: =A48 -> 2027 | B49: =C48+1 -> 46569 | C49: =B49+30 -> 46599 | D49: 1 | E49: =E48 -> 9515 | F49: =F48 -> 883.96507 | H49: =H48 -> 120 | I49: =I48 -> 170000 | J49: =J48 -> 16.254 | K49: =H49*E49 -> 1141800 | L49: =J49*E49 -> 154656.81 | M49: =I49+K49+L49 -> 1466456.8
A50: =A49 -> 2027 | B50: =C49+1 -> 46600 | C50: =B50+30 -> 46630 | D50: 1 | E50: =E49 -> 9515 | F50: =F49 -> 883.96507 | H50: =H49 -> 120 | I50: =I49 -> 170000 | J50: =J49 -> 16.254 | K50: =H50*E50 -> 1141800 | L50: =J50*E50 -> 154656.81 | M50: =I50+K50+L50 -> 1466456.8
A51: =A50+1 -> 2028 | B51: =C50+1 -> 46631 | C51: =B51+30-1 -> 46660 | D51: 1 | E51: =E50 -> 9515 | F51: =F50 -> 883.96507 | H51: =H50 -> 120 | I51: =I50 -> 170000 | J51: =J50 -> 16.254 | K51: =H51*E51 -> 1141800 | L51: =J51*E51 -> 154656.81 | M51: =I51+K51+L51 -> 1466456.8 | N51: =SUM(K39:K50) -> 13701600 | O51: =SUM(L39:L50) -> 1826423.3 | P51: =SUM(I39:I50) -> 2040000
A52: =A51 -> 2028 | B52: =C51+1 -> 46661 | C52: =B52+30 -> 46691 | D52: 1 | E52: =E51 -> 9515 | F52: =F51 -> 883.96507 | H52: =H51 -> 120 | I52: =I51 -> 170000 | J52: =J51 -> 16.254 | K52: =H52*E52 -> 1141800 | L52: =J52*E52 -> 154656.81 | M52: =I52+K52+L52 -> 1466456.8
A53: =A52 -> 2028 | B53: =C52+1 -> 46692 | C53: =B53+30-1 -> 46721 | D53: 1 | E53: =E52 -> 9515 | F53: =F52 -> 883.96507 | H53: =H52 -> 120 | I53: =I52 -> 170000 | J53: =J52 -> 16.254 | K53: =H53*E53 -> 1141800 | L53: =J53*E53 -> 154656.81 | M53: =I53+K53+L53 -> 1466456.8
A54: =A53 -> 2028 | B54: =C53+1 -> 46722 | C54: =B54+30 -> 46752 | D54: 1 | E54: =E53 -> 9515 | F54: =F53 -> 883.96507 | H54: =H53 -> 120 | I54: =I53 -> 170000 | J54: =J53 -> 16.254 | K54: =H54*E54 -> 1141800 | L54: =J54*E54 -> 154656.81 | M54: =I54+K54+L54 -> 1466456.8
A55: =A54 -> 2028 | B55: =C54+1 -> 46753 | C55: =B55+30 -> 46783 | D55: 1 | E55: =E54 -> 9515 | F55: =F54 -> 883.96507 | H55: =H54 -> 120 | I55: =I54 -> 170000 | J55: =J54*1.05 -> 17.0667 | K55: =H55*E55 -> 1141800 | L55: =J55*E55 -> 162389.65 | M55: =I55+K55+L55 -> 1474189.7
A56: =A55 -> 2028 | B56: =C55+1 -> 46784 | C56: =B56+30-2 -> 46812 | D56: 1 | E56: =E55 -> 9515 | F56: =F55 -> 883.96507 | H56: =H55 -> 120 | I56: =I55 -> 170000 | J56: =J55 -> 17.0667 | K56: =H56*E56 -> 1141800 | L56: =J56*E56 -> 162389.65 | M56: =I56+K56+L56 -> 1474189.7
A57: =A56 -> 2028 | B57: =C56+1 -> 46813 | C57: =B57+30 -> 46843 | D57: 1 | E57: =E56 -> 9515 | F57: =F56 -> 883.96507 | H57: =H56 -> 120 | I57: =I56 -> 170000 | J57: =J56 -> 17.0667 | K57: =H57*E57 -> 1141800 | L57: =J57*E57 -> 162389.65 | M57: =I57+K57+L57 -> 1474189.7
A58: =A57 -> 2028 | B58: =C57+1 -> 46844 | C58: =B58+30-1 -> 46873 | D58: 1 | E58: =E57 -> 9515 | F58: =F57 -> 883.96507 | H58: =H57 -> 120 | I58: =I57 -> 170000 | J58: =J57 -> 17.0667 | K58: =H58*E58 -> 1141800 | L58: =J58*E58 -> 162389.65 | M58: =I58+K58+L58 -> 1474189.7
A59: =A58 -> 2028 | B59: =C58+1 -> 46874 | C59: =B59+30 -> 46904 | D59: 1 | E59: =E58 -> 9515 | F59: =F58 -> 883.96507 | H59: =H58 -> 120 | I59: =I58 -> 170000 | J59: =J58 -> 17.0667 | K59: =H59*E59 -> 1141800 | L59: =J59*E59 -> 162389.65 | M59: =I59+K59+L59 -> 1474189.7
A60: =A59 -> 2028 | B60: =C59+1 -> 46905 | C60: =B60+30-1 -> 46934 | D60: 1 | E60: =E59 -> 9515 | F60: =F59 -> 883.96507 | H60: =H59 -> 120 | I60: =I59 -> 170000 | J60: =J59 -> 17.0667 | K60: =H60*E60 -> 1141800 | L60: =J60*E60 -> 162389.65 | M60: =I60+K60+L60 -> 1474189.7
A61: =A60 -> 2028 | B61: =C60+1 -> 46935 | C61: =B61+30 -> 46965 | D61: 1 | E61: =E60 -> 9515 | F61: =F60 -> 883.96507 | H61: =H60 -> 120 | I61: =I60 -> 170000 | J61: =J60 -> 17.0667 | K61: =H61*E61 -> 1141800 | L61: =J61*E61 -> 162389.65 | M61: =I61+K61+L61 -> 1474189.7
A62: =A61 -> 2028 | B62: =C61+1 -> 46966 | C62: =B62+30 -> 46996 | D62: 1 | E62: =E61 -> 9515 | F62: =F61 -> 883.96507 | H62: =H61 -> 120 | I62: =I61 -> 170000 | J62: =J61 -> 17.0667 | K62: =H62*E62 -> 1141800 | L62: =J62*E62 -> 162389.65 | M62: =I62+K62+L62 -> 1474189.7
A63: =A62+1 -> 2029 | B63: =C62+1 -> 46997 | C63: =B63+30-1 -> 47026 | D63: 1 | E63: =E62 -> 9515 | F63: =F62 -> 883.96507 | H63: =H62 -> 120 | I63: =I62 -> 170000 | J63: =J62 -> 17.0667 | K63: =H63*E63 -> 1141800 | L63: =J63*E63 -> 162389.65 | M63: =I63+K63+L63 -> 1474189.7 | N63: =SUM(K51:K62) -> 13701600 | O63: =SUM(L51:L62) -> 1917744.4 | P63: =SUM(I51:I62) -> 2040000
A64: =A63 -> 2029 | B64: =C63+1 -> 47027 | C64: =B64+30 -> 47057 | D64: 1 | E64: =E63 -> 9515 | F64: =F63 -> 883.96507 | H64: =H63 -> 120 | I64: =I63 -> 170000 | J64: =J63 -> 17.0667 | K64: =H64*E64 -> 1141800 | L64: =J64*E64 -> 162389.65 | M64: =I64+K64+L64 -> 1474189.7
A65: =A64 -> 2029 | B65: =C64+1 -> 47058 | C65: =B65+30-1 -> 47087 | D65: 1 | E65: =E64 -> 9515 | F65: =F64 -> 883.96507 | H65: =H64 -> 120 | I65: =I64 -> 170000 | J65: =J64 -> 17.0667 | K65: =H65*E65 -> 1141800 | L65: =J65*E65 -> 162389.65 | M65: =I65+K65+L65 -> 1474189.7
A66: =A65 -> 2029 | B66: =C65+1 -> 47088 | C66: =B66+30 -> 47118 | D66: 1 | E66: =E65 -> 9515 | F66: =F65 -> 883.96507 | H66: =H65 -> 120 | I66: =I65 -> 170000 | J66: =J65 -> 17.0667 | K66: =H66*E66 -> 1141800 | L66: =J66*E66 -> 162389.65 | M66: =I66+K66+L66 -> 1474189.7
A67: =A66 -> 2029 | B67: =C66+1 -> 47119 | C67: =B67+30 -> 47149 | D67: 1 | E67: =E66 -> 9515 | F67: =F66 -> 883.96507 | H67: =H66*1.15 -> 138 | I67: =I66*1.15 -> 195500 | J67: =J66*1.05 -> 17.920035 | K67: =H67*E67 -> 1313070 | L67: =J67*E67 -> 170509.13 | M67: =I67+K67+L67 -> 1679079.1
A68: =A67 -> 2029 | B68: =C67+1 -> 47150 | C68: =B68+30-3 -> 47177 | D68: 1 | E68: =E67 -> 9515 | F68: =F67 -> 883.96507 | H68: =H67 -> 138 | I68: =I67 -> 195500 | J68: =J67 -> 17.920035 | K68: =H68*E68 -> 1313070 | L68: =J68*E68 -> 170509.13 | M68: =I68+K68+L68 -> 1679079.1
A69: =A68 -> 2029 | B69: =C68+1 -> 47178 | C69: =B69+30 -> 47208 | D69: 1 | E69: =E68 -> 9515 | F69: =F68 -> 883.96507 | H69: =H68 -> 138 | I69: =I68 -> 195500 | J69: =J68 -> 17.920035 | K69: =H69*E69 -> 1313070 | L69: =J69*E69 -> 170509.13 | M69: =I69+K69+L69 -> 1679079.1
A70: =A69 -> 2029 | B70: =C69+1 -> 47209 | C70: =B70+30-1 -> 47238 | D70: 1 | E70: =E69 -> 9515 | F70: =F69 -> 883.96507 | H70: =H69 -> 138 | I70: =I69 -> 195500 | J70: =J69 -> 17.920035 | K70: =H70*E70 -> 1313070 | L70: =J70*E70 -> 170509.13 | M70: =I70+K70+L70 -> 1679079.1
A71: =A70 -> 2029 | B71: =C70+1 -> 47239 | C71: =B71+30 -> 47269 | D71: 1 | E71: =E70 -> 9515 | F71: =F70 -> 883.96507 | H71: =H70 -> 138 | I71: =I70 -> 195500 | J71: =J70 -> 17.920035 | K71: =H71*E71 -> 1313070 | L71: =J71*E71 -> 170509.13 | M71: =I71+K71+L71 -> 1679079.1
A72: =A71 -> 2029 | B72: =C71+1 -> 47270 | C72: =B72+30-1 -> 47299 | D72: 1 | E72: =E71 -> 9515 | F72: =F71 -> 883.96507 | H72: =H71 -> 138 | I72: =I71 -> 195500 | J72: =J71 -> 17.920035 | K72: =H72*E72 -> 1313070 | L72: =J72*E72 -> 170509.13 | M72: =I72+K72+L72 -> 1679079.1
A73: =A72 -> 2029 | B73: =C72+1 -> 47300 | C73: =B73+30 -> 47330 | D73: 1 | E73: =E72 -> 9515 | F73: =F72 -> 883.96507 | H73: =H72 -> 138 | I73: =I72 -> 195500 | J73: =J72 -> 17.920035 | K73: =H73*E73 -> 1313070 | L73: =J73*E73 -> 170509.13 | M73: =I73+K73+L73 -> 1679079.1
A74: =A73 -> 2029 | B74: =C73+1 -> 47331 | C74: =B74+30 -> 47361 | D74: 1 | E74: =E73 -> 9515 | F74: =F73 -> 883.96507 | H74: =H73 -> 138 | I74: =I73 -> 195500 | J74: =J73 -> 17.920035 | K74: =H74*E74 -> 1313070 | L74: =J74*E74 -> 170509.13 | M74: =I74+K74+L74 -> 1679079.1
A75: =A74+1 -> 2030 | B75: =C74+1 -> 47362 | C75: =B75+30-1 -> 47391 | D75: 1 | E75: =E74 -> 9515 | F75: =F74 -> 883.96507 | H75: =H74 -> 138 | I75: =I74 -> 195500 | J75: =J74 -> 17.920035 | K75: =H75*E75 -> 1313070 | L75: =J75*E75 -> 170509.13 | M75: =I75+K75+L75 -> 1679079.1 | N75: =SUM(K63:K74) -> 15071760 | O75: =SUM(L63:L74) -> 2013631.7 | P75: =SUM(I63:I74) -> 2244000
A76: =A75 -> 2030 | B76: =C75+1 -> 47392 | C76: =B76+30 -> 47422 | D76: 1 | E76: =E75 -> 9515 | F76: =F75 -> 883.96507 | H76: =H75 -> 138 | I76: =I75 -> 195500 | J76: =J75 -> 17.920035 | K76: =H76*E76 -> 1313070 | L76: =J76*E76 -> 170509.13 | M76: =I76+K76+L76 -> 1679079.1
A77: =A76 -> 2030 | B77: =C76+1 -> 47423 | C77: =B77+30-1 -> 47452 | D77: 1 | E77: =E76 -> 9515 | F77: =F76 -> 883.96507 | H77: =H76 -> 138 | I77: =I76 -> 195500 | J77: =J76 -> 17.920035 | K77: =H77*E77 -> 1313070 | L77: =J77*E77 -> 170509.13 | M77: =I77+K77+L77 -> 1679079.1
A78: =A77 -> 2030 | B78: =C77+1 -> 47453 | C78: =B78+30 -> 47483 | D78: 1 | E78: =E77 -> 9515 | F78: =F77 -> 883.96507 | H78: =H77 -> 138 | I78: =I77 -> 195500 | J78: =J77 -> 17.920035 | K78: =H78*E78 -> 1313070 | L78: =J78*E78 -> 170509.13 | M78: =I78+K78+L78 -> 1679079.1
A79: =A78 -> 2030 | B79: =C78+1 -> 47484 | C79: =B79+30 -> 47514 | D79: 1 | E79: =E78 -> 9515 | F79: =F78 -> 883.96507 | H79: =H78 -> 138 | I79: =I78 -> 195500 | J79: =J78*1.05 -> 18.816037 | K79: =H79*E79 -> 1313070 | L79: =J79*E79 -> 179034.59 | M79: =I79+K79+L79 -> 1687604.6
A80: =A79 -> 2030 | B80: =C79+1 -> 47515 | C80: =B80+30-3 -> 47542 | D80: 1 | E80: =E79 -> 9515 | F80: =F79 -> 883.96507 | H80: =H79 -> 138 | I80: =I79 -> 195500 | J80: =J79 -> 18.816037 | K80: =H80*E80 -> 1313070 | L80: =J80*E80 -> 179034.59 | M80: =I80+K80+L80 -> 1687604.6
A81: =A80 -> 2030 | B81: =C80+1 -> 47543 | C81: =B81+30 -> 47573 | D81: 1 | E81: =E80 -> 9515 | F81: =F80 -> 883.96507 | H81: =H80 -> 138 | I81: =I80 -> 195500 | J81: =J80 -> 18.816037 | K81: =H81*E81 -> 1313070 | L81: =J81*E81 -> 179034.59 | M81: =I81+K81+L81 -> 1687604.6
A82: =A81 -> 2030 | B82: =C81+1 -> 47574 | C82: =B82+30-1 -> 47603 | D82: 1 | E82: =E81 -> 9515 | F82: =F81 -> 883.96507 | H82: =H81 -> 138 | I82: =I81 -> 195500 | J82: =J81 -> 18.816037 | K82: =H82*E82 -> 1313070 | L82: =J82*E82 -> 179034.59 | M82: =I82+K82+L82 -> 1687604.6
A83: =A82 -> 2030 | B83: =C82+1 -> 47604 | C83: =B83+30 -> 47634 | D83: 1 | E83: =E82 -> 9515 | F83: =F82 -> 883.96507 | H83: =H82 -> 138 | I83: =I82 -> 195500 | J83: =J82 -> 18.816037 | K83: =H83*E83 -> 1313070 | L83: =J83*E83 -> 179034.59 | M83: =I83+K83+L83 -> 1687604.6
A84: =A83 -> 2030 | B84: =C83+1 -> 47635 | C84: =B84+30-1 -> 47664 | D84: 1 | E84: =E83 -> 9515 | F84: =F83 -> 883.96507 | H84: =H83 -> 138 | I84: =I83 -> 195500 | J84: =J83 -> 18.816037 | K84: =H84*E84 -> 1313070 | L84: =J84*E84 -> 179034.59 | M84: =I84+K84+L84 -> 1687604.6
A85: =A84 -> 2030 | B85: =C84+1 -> 47665 | C85: =B85+30 -> 47695 | D85: 1 | E85: =E84 -> 9515 | F85: =F84 -> 883.96507 | H85: =H84 -> 138 | I85: =I84 -> 195500 | J85: =J84 -> 18.816037 | K85: =H85*E85 -> 1313070 | L85: =J85*E85 -> 179034.59 | M85: =I85+K85+L85 -> 1687604.6
A86: =A85 -> 2030 | B86: =C85+1 -> 47696 | C86: =B86+30 -> 47726 | D86: 1 | E86: =E85 -> 9515 | F86: =F85 -> 883.96507 | H86: =H85 -> 138 | I86: =I85 -> 195500 | J86: =J85 -> 18.816037 | K86: =H86*E86 -> 1313070 | L86: =J86*E86 -> 179034.59 | M86: =I86+K86+L86 -> 1687604.6
A87: =A86+1 -> 2031 | B87: =C86+1 -> 47727 | C87: =B87+30-1 -> 47756 | D87: 1 | E87: =E86 -> 9515 | F87: =F86 -> 883.96507 | H87: =H86 -> 138 | I87: =I86 -> 195500 | J87: =J86 -> 18.816037 | K87: =H87*E87 -> 1313070 | L87: =J87*E87 -> 179034.59 | M87: =I87+K87+L87 -> 1687604.6 | N87: =SUM(K75:K86) -> 15756840 | O87: =SUM(L75:L86) -> 2114313.2 | P87: =SUM(I75:I86) -> 2346000
A88: =A87 -> 2031 | B88: =C87+1 -> 47757 | C88: =B88+30 -> 47787 | D88: 1 | E88: =E87 -> 9515 | F88: =F87 -> 883.96507 | H88: =H87 -> 138 | I88: =I87 -> 195500 | J88: =J87 -> 18.816037 | K88: =H88*E88 -> 1313070 | L88: =J88*E88 -> 179034.59 | M88: =I88+K88+L88 -> 1687604.6
A89: =A88 -> 2031 | B89: =C88+1 -> 47788 | C89: =B89+30-1 -> 47817 | D89: 1 | E89: =E88 -> 9515 | F89: =F88 -> 883.96507 | H89: =H88 -> 138 | I89: =I88 -> 195500 | J89: =J88 -> 18.816037 | K89: =H89*E89 -> 1313070 | L89: =J89*E89 -> 179034.59 | M89: =I89+K89+L89 -> 1687604.6
A90: =A89 -> 2031 | B90: =C89+1 -> 47818 | C90: =B90+30 -> 47848 | D90: 1 | E90: =E89 -> 9515 | F90: =F89 -> 883.96507 | H90: =H89 -> 138 | I90: =I89 -> 195500 | J90: =J89 -> 18.816037 | K90: =H90*E90 -> 1313070 | L90: =J90*E90 -> 179034.59 | M90: =I90+K90+L90 -> 1687604.6
A91: =A90 -> 2031 | B91: =C90+1 -> 47849 | C91: =B91+30 -> 47879 | D91: 1 | E91: =E90 -> 9515 | F91: =F90 -> 883.96507 | H91: =H90 -> 138 | I91: =I90 -> 195500 | J91: =J90*1.05 -> 19.756839 | K91: =H91*E91 -> 1313070 | L91: =J91*E91 -> 187986.32 | M91: =I91+K91+L91 -> 1696556.3
A92: =A91 -> 2031 | B92: =C91+1 -> 47880 | C92: =B92+30-3 -> 47907 | D92: 1 | E92: =E91 -> 9515 | F92: =F91 -> 883.96507 | H92: =H91 -> 138 | I92: =I91 -> 195500 | J92: =J91 -> 19.756839 | K92: =H92*E92 -> 1313070 | L92: =J92*E92 -> 187986.32 | M92: =I92+K92+L92 -> 1696556.3
A93: =A92 -> 2031 | B93: =C92+1 -> 47908 | C93: =B93+30 -> 47938 | D93: 1 | E93: =E92 -> 9515 | F93: =F92 -> 883.96507 | H93: =H92 -> 138 | I93: =I92 -> 195500 | J93: =J92 -> 19.756839 | K93: =H93*E93 -> 1313070 | L93: =J93*E93 -> 187986.32 | M93: =I93+K93+L93 -> 1696556.3
A94: =A93 -> 2031 | B94: =C93+1 -> 47939 | C94: =B94+30-1 -> 47968 | D94: 1 | E94: =E93 -> 9515 | F94: =F93 -> 883.96507 | H94: =H93 -> 138 | I94: =I93 -> 195500 | J94: =J93 -> 19.756839 | K94: =H94*E94 -> 1313070 | L94: =J94*E94 -> 187986.32 | M94: =I94+K94+L94 -> 1696556.3
A95: =A94 -> 2031 | B95: =C94+1 -> 47969 | C95: =B95+30 -> 47999 | D95: 1 | E95: =E94 -> 9515 | F95: =F94 -> 883.96507 | H95: =H94 -> 138 | I95: =I94 -> 195500 | J95: =J94 -> 19.756839 | K95: =H95*E95 -> 1313070 | L95: =J95*E95 -> 187986.32 | M95: =I95+K95+L95 -> 1696556.3
A96: =A95 -> 2031 | B96: =C95+1 -> 48000 | C96: =B96+30-1 -> 48029 | D96: 1 | E96: =E95 -> 9515 | F96: =F95 -> 883.96507 | H96: =H95 -> 138 | I96: =I95 -> 195500 | J96: =J95 -> 19.756839 | K96: =H96*E96 -> 1313070 | L96: =J96*E96 -> 187986.32 | M96: =I96+K96+L96 -> 1696556.3
A97: =A96 -> 2031 | B97: =C96+1 -> 48030 | C97: =B97+30 -> 48060 | D97: 1 | E97: =E96 -> 9515 | F97: =F96 -> 883.96507 | H97: =H96 -> 138 | I97: =I96 -> 195500 | J97: =J96 -> 19.756839 | K97: =H97*E97 -> 1313070 | L97: =J97*E97 -> 187986.32 | M97: =I97+K97+L97 -> 1696556.3
A98: =A97 -> 2031 | B98: =C97+1 -> 48061 | C98: =B98+30 -> 48091 | D98: 1 | E98: =E97 -> 9515 | F98: =F97 -> 883.96507 | H98: =H97 -> 138 | I98: =I97 -> 195500 | J98: =J97 -> 19.756839 | K98: =H98*E98 -> 1313070 | L98: =J98*E98 -> 187986.32 | M98: =I98+K98+L98 -> 1696556.3
A99: =A98+1 -> 2032 | B99: =C98+1 -> 48092 | C99: =B99+30-1 -> 48121 | D99: 1 | E99: =E98 -> 9515 | F99: =F98 -> 883.96507 | H99: =H98 -> 138 | I99: =I98 -> 195500 | J99: =J98 -> 19.756839 | K99: =H99*E99 -> 1313070 | L99: =J99*E99 -> 187986.32 | M99: =I99+K99+L99 -> 1696556.3 | N99: =SUM(K87:K98) -> 15756840 | O99: =SUM(L87:L98) -> 2220028.9 | P99: =SUM(I87:I98) -> 2346000
A100: =A99 -> 2032 | B100: =C99+1 -> 48122 | C100: =B100+30 -> 48152 | D100: 1 | E100: =E99 -> 9515 | F100: =F99 -> 883.96507 | H100: =H99 -> 138 | I100: =I99 -> 195500 | J100: =J99 -> 19.756839 | K100: =H100*E100 -> 1313070 | L100: =J100*E100 -> 187986.32 | M100: =I100+K100+L100 -> 1696556.3
A101: =A100 -> 2032 | B101: =C100+1 -> 48153 | C101: =B101+30-1 -> 48182 | D101: 1 | E101: =E100 -> 9515 | F101: =F100 -> 883.96507 | H101: =H100 -> 138 | I101: =I100 -> 195500 | J101: =J100 -> 19.756839 | K101: =H101*E101 -> 1313070 | L101: =J101*E101 -> 187986.32 | M101: =I101+K101+L101 -> 1696556.3
A102: =A101 -> 2032 | B102: =C101+1 -> 48183 | C102: =B102+30 -> 48213 | D102: 1 | E102: =E101 -> 9515 | F102: =F101 -> 883.96507 | H102: =H101 -> 138 | I102: =I101 -> 195500 | J102: =J101 -> 19.756839 | K102: =H102*E102 -> 1313070 | L102: =J102*E102 -> 187986.32 | M102: =I102+K102+L102 -> 1696556.3
N103: =SUM(K99:K102) -> 5252280 | O103: =SUM(L99:L102) -> 751945.28 | P103: =SUM(I99:I102) -> 782000
I104: =SUM(I31:I102) -> 13158000 | K104: =SUM(K31:K102) -> 88375320 | L104: =SUM(L31:L102) -> 12022424 | M104: =SUM(M31:M102) -> 1.1355574e+08 | N104: =SUM(N31:N103) -> 88375320 | O104: =SUM(O31:O103) -> 12022424 | P104: =SUM(P31:P103) -> 13158000

Sheet CAPEX and PM
A1: Calculation of Amortisation of Siemens own Investment
A2: Investment name | B2: Fitout | D2: FY | F2: 2026 | G2: =F2+1 -> 2027 | H2: =G2+1 -> 2028 | I2: =H2+1 -> 2029 | J2: =I2+1 -> 2030 | K2: =J2+1 -> 2031 | L2: =K2+1 -> 2032 | M2: =L2+1 -> 2033 | N2: =M2+1 -> 2034 | O2: =N2+1 -> 2035
A3: Investment Cost | B3: =B6+B12+B18 -> 34000000 | D3: Month needed | E3: =SUM(F3:N3) -> 72 | F3: 8 | G3: 12 | H3: 12 | I3: 12 | J3: 12 | K3: 12 | L3: 4 | M3: 0 | N3: 0 | O3: 0
A4: Interest Rate | B4: =+'Rent Calculation'!F29 -> 0.0711 | D4: Month left | E4: =E3-SUM(F3:N3) -> 0
A6: Investment Cost | B6: 14000000 | D6: Annual Depreciation Rate | F6: =IF(F3<>0,$B$6/$B$7,0) -> 2333333.3 | G6: =IF(G3<>0,$B$6/$B$7,0) -> 2333333.3 | H6: =IF(H3<>0,$B$6/$B$7,0) -> 2333333.3 | I6: =IF(I3<>0,$B$6/$B$7,0) -> 2333333.3 | J6: =IF(J3<>0,$B$6/$B$7,0) -> 2333333.3 | K6: =IF(K3<>0,$B$6/$B$7,0) -> 2333333.3 | L6: =IF(L3<>0,$B$6/$B$7,0) -> 2333333.3 | M6: =IF(M3<>0,$B$6/$B$7,0) -> 0 | ... O6: =IF(O3<>0,$B$6/$B$7,0) -> 0
A7: Depreciation Time | B7: =E3/12 -> 6 | D7: used Depreciation | F7: =F6/12*F3 -> 1555555.6 | G7: =G6/12*G3 -> 2333333.3 | H7: =H6/12*H3 -> 2333333.3 | I7: =I6/12*I3 -> 2333333.3 | J7: =J6/12*J3 -> 2333333.3 | K7: =K6/12*K3 -> 2333333.3 | L7: =L6/12*L3 -> 777777.78 | M7: =M6/12*M3 -> 0 | ... O7: =O6/12*O3 -> 0
D9: Month needed | E9: =SUM(F9:N9) -> 30 | F9: 8 | G9: 12 | H9: 10 | I9: 0 | J9: 0 | K9: 0 | L9: 0 | M9: 0 | N9: 0 | O9: 0
D10: Month left | E10: 0
A12: Investment Cost | B12: 5000000 | D12: Annual Depreciation Rate | F12: =IF(F9<>0,$B$12/$B$13,0) -> 2000000 | G12: =IF(G9<>0,$B$12/$B$13,0) -> 2000000 | H12: =IF(H9<>0,$B$12/$B$13,0) -> 2000000 | I12: =IF(I9<>0,$B$12/$B$13,0) -> 0 | J12: =IF(J9<>0,$B$12/$B$13,0) -> 0 | K12: =IF(K9<>0,$B$12/$B$13,0) -> 0 | L12: =IF(L9<>0,$B$12/$B$13,0) -> 0 | M12: =IF(M9<>0,$B$12/$B$13,0) -> 0 | ... O12: =IF(O9<>0,$B$12/$B$13,0) -> 0
A13: Depreciation Time | B13: =E9/12 -> 2.5 | D13: used Depreciation | F13: =F12/12*F3 -> 1333333.3 | G13: =G12/12*G9 -> 2000000 | H13: =H12/12*H9 -> 1666666.7 | I13: =I12/12*I9 -> 0 | J13: =J12/12*J9 -> 0 | K13: =K12/12*K9 -> 0 | L13: =L12/12*L9 -> 0 | M13: =M12/12*M9 -> 0 | N13: =N12/12*N9 -> 0 | O13: =O12/12*O9 -> 0
D15: Month needed | E15: =SUM(F15:N15) -> 48 | F15: 8 | G15: 12 | H15: 12 | I15: 12 | J15: 4 | K15: 0 | L15: 0 | M15: 0 | N15: 0 | O15: 0
D16: Month left | E16: =E15-SUM(F15:N15) -> 0
A18: Investment Cost | B18: 15000000 | D18: Annual Depreciation Rate | F18: =IF(F15<>0,$B$18/$B$19,0) -> 3750000 | G18: =IF(G15<>0,$B$18/$B$19,0) -> 3750000 | H18: =IF(H15<>0,$B$18/$B$19,0) -> 3750000 | I18: =IF(I15<>0,$B$18/$B$19,0) -> 3750000 | J18: =IF(J15<>0,$B$18/$B$19,0) -> 3750000 | K18: =IF(K15<>0,$B$18/$B$19,0) -> 0 | L18: =IF(L15<>0,$B$18/$B$19,0) -> 0 | M18: =IF(M15<>0,$B$18/$B$19,0) -> 0 | ... O18: =IF(O15<>0,$B$18/$B$19,0) -> 0
A19: Depreciation Time | B19: =E15/12 -> 4 | D19: used Depreciation | F19: =F18/12*F15 -> 2500000 | G19: =G18/12*G15 -> 3750000 | H19: =H18/12*H15 -> 3750000 | I19: =I18/12*I15 -> 3750000 | J19: =J18/12*J15 -> 1250000 | K19: =K18/12*K15 -> 0 | L19: =L18/12*L15 -> 0 | M19: =M18/12*M15 -> 0 | ... O19: =O18/12*O15 -> 0
A21: Area Sq. Fit | B21: =+'Rent Calculation'!F21 -> 9515 | D21: Book value at Begin of FY | F21: =B3 -> 34000000 | G21: =F22 -> 28611111 | H21: =G22 -> 20527778 | I21: =H22 -> 12777778 | J21: =I22 -> 6694444.4 | K21: =J22 -> 3111111.1 | L21: =K22 -> 777777.78 | M21: =L22 -> -2.6775524e-09 | N21: =M22 -> -2.6775524e-09 | O21: =N22 -> -2.6775524e-09
A22: Area Sq. Mtr | B22: =+B21/10.764 -> 883.96507 | D22: Book value at End of FY | F22: =F21-F27 -> 28611111 | G22: =G21-G27 -> 20527778 | H22: =H21-H27 -> 12777778 | I22: =I21-I27 -> 6694444.4 | J22: =J21-J27 -> 3111111.1 | K22: =K21-K27 -> 777777.78 | L22: =L21-L27 -> -2.6775524e-09 | M22: =M21-M27 -> -2.6775524e-09 | ... O22: =O21-O27 -> -2.6775524e-09
A23: Investment year* | B23: =F2 -> 2026 | D23: Average Net Book Value FY | F23: =(F21+F22)/2 -> 31305556 | G23: =(G21+G22)/2 -> 24569444 | H23: =(H21+H22)/2 -> 16652778 | I23: =(I21+I22)/2 -> 9736111.1 | J23: =(J21+J22)/2 -> 4902777.8 | K23: =(K21+K22)/2 -> 1944444.4 | L23: =(L21+L22)/2 -> 388888.89 | M23: =(M21+M22)/2 -> -2.6775524e-09 | ... O23: =(O21+O22)/2 -> -2.6775524e-09
D26: Impted Interest | E26: =SUM(F26:N26) -> 5621508.3 | F26: =F23*$B$4/12*F3 -> 1483883.3 | G26: =G23*$B$4/12*G3 -> 1746887.5 | H26: =H23*$B$4/12*H3 -> 1184012.5 | I26: =I23*$B$4/12*I3 -> 692237.5 | J26: =J23*$B$4 -> 348587.5 | K26: =K23*$B$4 -> 138250 | L26: =L23*$B$4 -> 27650 | M26: =M23*$B$4 -> -1.9037398e-10 | N26: =N23*$B$4 -> -1.9037398e-10 | O26: =O23*$B$4 -> -1.9037398e-10
A27: Test if refinace is ok (0%) | B27: =E30*E9 -> 16508962 | D27: Used Depreciation | E27: =SUM(F27:N27) -> 34000000 | F27: =F7+F13+F19 -> 5388888.9 | G27: =G7+G13+G19 -> 8083333.3 | H27: =H7+H13+H19 -> 7750000 | I27: =I7+I13+I19 -> 6083333.3 | J27: =J7+J13+J19 -> 3583333.3 | K27: =K7+K13+K19 -> 2333333.3 | L27: =L7+L13+L19 -> 777777.78 | M27: =M7+M13+M19 -> 0 | ... O27: =O7+O13+O19 -> 0
A29: per sq. ft. | B29: =+E30/B21 -> 57.834864 | F29: =SUM(F26:F28) -> 6872772.2 | G29: =SUM(G26:G28) -> 9830220.8 | H29: =SUM(H26:H28) -> 8934012.5 | I29: =SUM(I26:I28) -> 6775570.8 | J29: =SUM(J26:J28) -> 3931920.8 | K29: =SUM(K26:K28) -> 2471583.3 | L29: =SUM(L26:L28) -> 805427.78 | M29: =SUM(M26:M28) -> -1.9037398e-10 | ... O29: =SUM(O26:O28) -> -1.9037398e-10
A30: per sq. mtr | B30: =+E30/B22 -> 622.53447 | D30: Monthly Value | E30: =IFERROR(SUM(F26:N27)/E3,0) -> 550298.73
A36: Investment name | B36: Capex | D36: FY | F36: =F2 -> 2026 | G36: =F36+1 -> 2027 | H36: =G36+1 -> 2028 | I36: =H36+1 -> 2029 | J36: =I36+1 -> 2030 | K36: =J36+1 -> 2031 | L36: =K36+1 -> 2032 | M36: =L36+1 -> 2033 | N36: =M36+1 -> 2034 | O36: =N36+1 -> 2035
A37: Investment Cost | B37: =SUM(F38:O38) -> 43000000
A38: Interest Rate | B38: =B4 -> 0.0711 | D38: Investment | F38: 14000000 | G38: 12000000 | H38: 5000000 | I38: 6000000 | J38: 6000000
A40: Investment Cost | B40: =+F38 -> 14000000 | D40: Month needed | E40: =SUM(F40:O40) -> 72 | F40: 8 | G40: 12 | H40: 12 | I40: 12 | J40: 12 | K40: 12 | L40: 4
A41: Depreciation Time | B41: =E40/12 -> 6 | D41: Month left | E41: =E40-SUM(F40:N40) -> 0
D42: Annual Depreciation Rate | F42: =IF(F40<>0,$F$38/$B$41,0) -> 2333333.3 | G42: =IF(G40<>0,$F$38/$B$41,0) -> 2333333.3 | H42: =IF(H40<>0,$F$38/$B$41,0) -> 2333333.3 | I42: =IF(I40<>0,$F$38/$B$41,0) -> 2333333.3 | J42: =IF(J40<>0,$F$38/$B$41,0) -> 2333333.3 | K42: =IF(K40<>0,$F$38/$B$41,0) -> 2333333.3 | L42: =IF(L40<>0,$F$38/$B$41,0) -> 2333333.3 | M42: =IF(M40<>0,$F$38/$B$41,0) -> 0 | ... O42: =IF(O40<>0,$F$38/$B$41,0) -> 0
D43: used Depreciation | F43: =F42/12*F40 -> 1555555.6 | G43: =G42/12*G40 -> 2333333.3 | H43: =H42/12*H40 -> 2333333.3 | I43: =I42/12*I40 -> 2333333.3 | J43: =J42/12*J40 -> 2333333.3 | K43: =K42/12*K40 -> 2333333.3 | L43: =L42/12*L40 -> 777777.78 | M43: =M42/12*M40 -> 0 | ... O43: =O42/12*O40 -> 0
A45: Investment Cost | B45: =+G38 -> 12000000 | D45: Month needed | E45: =SUM(F45:O45) -> 60 | G45: 8 | H45: 12 | I45: 12 | J45: 12 | K45: 12 | L45: 4
A46: Depreciation Time | B46: =E45/12 -> 5 | D46: Month left | E46: =E45-SUM(F45:N45) -> 0
D47: Annual Depreciation Rate | G47: =IF(G45<>0,$G$38/($E$45/12),0) -> 2400000 | H47: =IF(H45<>0,$G$38/($E$45/12),0) -> 2400000 | I47: =IF(I45<>0,$G$38/($E$45/12),0) -> 2400000 | J47: =IF(J45<>0,$G$38/($E$45/12),0) -> 2400000 | K47: =IF(K45<>0,$G$38/($E$45/12),0) -> 2400000 | L47: =IF(L45<>0,$G$38/($E$45/12),0) -> 2400000 | M47: =IF(M45<>0,$G$38/($E$45/12),0) -> 0 | N47: =IF(N45<>0,$G$38/($E$45/12),0) -> 0 | O47: =IF(O45<>0,$G$38/($E$45/12),0) -> 0
D48: used Depreciation | G48: =G47/12*G45 -> 1600000 | H48: =H47/12*H45 -> 2400000 | I48: =I47/12*I45 -> 2400000 | J48: =J47/12*J45 -> 2400000 | K48: =K47/12*K45 -> 2400000 | L48: =L47/12*L45 -> 800000 | M48: =M47/12*M45 -> 0 | N48: =N47/12*N45 -> 0 | O48: =O47/12*O45 -> 0
A50: Investment Cost | B50: =+H38 -> 5000000 | D50: Month needed | E50: =SUM(F50:O50) -> 48 | H50: 8 | I50: 12 | J50: 12 | K50: 12 | L50: 4
A51: Depreciation Time | B51: =E50/12 -> 4 | D51: Month left | E51: =E50-SUM(F50:N50) -> 0
D52: Annual Depreciation Rate | H52: =IF(H50<>0,$H$38/($E$50/12),0) -> 1250000 | I52: =IF(I50<>0,$H$38/($E$50/12),0) -> 1250000 | J52: =IF(J50<>0,$H$38/($E$50/12),0) -> 1250000 | K52: =IF(K50<>0,$H$38/($E$50/12),0) -> 1250000 | L52: =IF(L50<>0,$H$38/($E$50/12),0) -> 1250000 | M52: =IF(M50<>0,$H$38/($E$50/12),0) -> 0 | N52: =IF(N50<>0,$H$38/($E$50/12),0) -> 0 | O52: =IF(O50<>0,$H$38/($E$50/12),0) -> 0
D53: used Depreciation | H53: =H52/12*H50 -> 833333.33 | I53: =I52/12*I50 -> 1250000 | J53: =J52/12*J50 -> 1250000 | K53: =K52/12*K50 -> 1250000 | L53: =L52/12*L50 -> 416666.67 | M53: =M52/12*M50 -> 0 | N53: =N52/12*N50 -> 0 | O53: =O52/12*O50 -> 0
A55: Investment Cost | B55: =+I38 -> 6000000 | D55: Month needed | E55: =SUM(F55:O55) -> 36 | I55: 8 | J55: 12 | K55: 12 | L55: 4 | M55: 0
A56: Depreciation Time | B56: =E55/12 -> 3 | D56: Month left | E56: =E55-SUM(F55:N55) -> 0
D57: Annual Depreciation Rate | I57: =IF(I55<>0,$I$38/($E$55/12),0) -> 2000000 | J57: =IF(J55<>0,$I$38/($E$55/12),0) -> 2000000 | K57: =IF(K55<>0,$I$38/($E$55/12),0) -> 2000000 | L57: =IF(L55<>0,$I$38/($E$55/12),0) -> 2000000 | M57: =IF(M55<>0,$I$38/($E$55/12),0) -> 0 | N57: =IF(N55<>0,$I$38/($E$55/12),0) -> 0 | O57: =IF(O55<>0,$I$38/($E$55/12),0) -> 0
D58: used Depreciation | I58: =I57/12*I55 -> 1333333.3 | J58: =J57/12*J55 -> 2000000 | K58: =K57/12*K55 -> 2000000 | L58: =L57/12*L55 -> 666666.67 | M58: =M57/12*M55 -> 0 | N58: =N57/12*N55 -> 0 | O58: =O57/12*O55 -> 0
A60: Investment Cost | B60: =J38 -> 6000000 | D60: Month needed | E60: =SUM(F60:O60) -> 24 | J60: 8 | K60: 12 | L60: 4 | M60: 0 | N60: 0 | O60: 0
A61: Depreciation Time | B61: =E60/12 -> 2 | D61: Month left | E61: =E60-SUM(F60:O60) -> 0
D62: Annual Depreciation Rate | J62: =IF(J60<>0,$I$38/($E$60/12),0) -> 3000000 | K62: =IF(K60<>0,$I$38/($E$60/12),0) -> 3000000 | L62: =IF(L60<>0,$I$38/($E$60/12),0) -> 3000000 | M62: =IF(M60<>0,$J$38/$B$41,0) -> 0 | N62: =IF(N60<>0,$J$38/$B$41,0) -> 0 | O62: =IF(O60<>0,$J$38/$B$41,0) -> 0
D63: used Depreciation | J63: =J62/12*J60 -> 2000000 | K63: =K62/12*K60 -> 3000000 | L63: =L62/12*L60 -> 1000000 | M63: =M62/12*M60 -> 0 | N63: =N62/12*N60 -> 0 | O63: =O62/12*O60 -> 0
A65: Investment Cost | B65: =+K38 -> 0 | D65: Month needed | E65: =SUM(F65:O65) -> 0 | K65: 0 | L65: 0 | M65: 0 | N65: 0 | O65: 0
A66: Depreciation Time | D66: Month left | E66: =E65-SUM(F65:O65) -> 0
D67: Annual Depreciation Rate | K67: =IF(K65<>0,$K$38/$B$41,0) -> 0 | L67: =IF(L65<>0,$K$38/$B$41,0) -> 0 | M67: =IF(M65<>0,$K$38/$B$41,0) -> 0 | N67: =IF(N65<>0,$K$38/$B$41,0) -> 0 | O67: =IF(O65<>0,$K$38/$B$41,0) -> 0
D68: used Depreciation | K68: =K67/12*K65 -> 0 | L68: =L67/12*L65 -> 0 | M68: =M67/12*M65 -> 0 | N68: =N67/12*N65 -> 0 | O68: =O67/12*O65 -> 0
A70: Investment Cost | B70: =+L38 -> 0 | D70: Month needed | E70: =SUM(F70:O70) -> 0 | L70: 0 | M70: 0 | N70: 0 | O70: 0
A71: Depreciation Time | D71: Month left | E71: =E70-SUM(F70:O70) -> 0
D72: Annual Depreciation Rate | L72: =IF(L70<>0,$L$38/$B$41,0) -> 0 | M72: =IF(M70<>0,$L$38/$B$41,0) -> 0 | N72: =IF(N70<>0,$L$38/$B$41,0) -> 0 | O72: =IF(O70<>0,$K$38/$B$41,0) -> 0
D73: used Depreciation | L73: =L72/12*L70 -> 0 | M73: =M72/12*M70 -> 0 | N73: =N72/12*N70 -> 0 | O73: =O72/12*O70 -> 0
A75: Investment Cost | B75: =+M38 -> 0 | D75: Month needed | E75: =SUM(F75:O75) -> 0 | M75: 0 | N75: 0 | O75: 0
A76: Depreciation Time | D76: Month left | E76: =E75-SUM(F75:O75) -> 0
D77: Annual Depreciation Rate | M77: =IF(M75<>0,$M$38/$B$41,0) -> 0 | N77: =IF(N75<>0,$M$38/$B$41,0) -> 0 | O77: =IF(O75<>0,$K$38/$B$41,0) -> 0
D78: used Depreciation | M78: =M77/12*M75 -> 0 | N78: =N77/12*N75 -> 0 | O78: =O77/12*O75 -> 0
A80: Investment Cost | B80: =+N38 -> 0 | D80: Month needed | E80: =SUM(F80:O80) -> 0 | N80: 0 | O80: 0
A81: Depreciation Time | D81: Month left | E81: =E80-SUM(F80:O80) -> 0
D82: Annual Depreciation Rate | N82: =IF(N80<>0,$M$38/$B$41,0) -> 0 | O82: =IF(O80<>0,$K$38/$B$41,0) -> 0
D83: used Depreciation | N83: =N82/12*N80 -> 0 | O83: =O82/12*O80 -> 0
A85: Investment Cost | B85: =O38 -> 0 | D85: Month needed | E85: =SUM(F85:O85) -> 0 | O85: 0
A86: Depreciation Time | D86: Month left | E86: =E85-SUM(F85:O85) -> 0
D87: Annual Depreciation Rate | O87: =IF(O85<>0,$K$38/$B$41,0) -> 0
D88: used Depreciation | O88: =O87/12*O85 -> 0
A90: Area Sq. Fit | B90: =B21 -> 9515 | D90: Book value at Begin of FY | F90: =+F38 -> 14000000 | G90: =+F91+G38 -> 24444444 | H90: =+G91+H38 -> 25511111 | I90: =+H91+I38 -> 25944444 | J90: =+I91+J38 -> 24627778 | K90: =+J91+K38 -> 14644444 | L90: =+K91+L38 -> 3661111.1 | M90: =+L91+M38 -> 0 | N90: =+M91+N38 -> 0 | O90: =+N91+O38 -> 0
A91: Area Sq. Mtr | B91: =+B90/10.764 -> 883.96507 | D91: Book value at End of FY | F91: =F90-F96 -> 12444444 | G91: =G90-G96 -> 20511111 | H91: =H90-H96 -> 19944444 | I91: =I90-I96 -> 18627778 | J91: =J90-J96 -> 14644444 | K91: =K90-K96 -> 3661111.1 | L91: =L90-L96 -> 0 | M91: =M90-M96 -> 0 | ... O91: =O90-O96 -> 0
A92: Investment year* | B92: =B23 -> 2026 | D92: Average Net Book Value FY | F92: =(F90+F91)/2 -> 13222222 | G92: =(G90+G91)/2 -> 22477778 | H92: =(H90+H91)/2 -> 22727778 | I92: =(I90+I91)/2 -> 22286111 | J92: =(J90+J91)/2 -> 19636111 | K92: =(K90+K91)/2 -> 9152777.8 | L92: =(L90+L91)/2 -> 1830555.6 | M92: =(M90+M91)/2 -> 0 | ... O92: =(O90+O91)/2 -> 0
D95: Impted Interest | E95: =SUM(F95:O95) -> 7515665 | F95: =F92*$B$38/12*F40 -> 626733.33 | G95: =G92*$B$38/12*G40 -> 1598170 | H95: =H92*$B$38/12*H40 -> 1615945 | I95: =I92*$B$38/12*I40 -> 1584542.5 | J95: =J92*$B$38/12*J40 -> 1396127.5 | K95: =K92*$B$38/12*K40 -> 650762.5 | L95: =L92*$B$38/12*L40 -> 43384.167 | M95: =M92*$B$38/12*M40 -> 0 | N95: =N92*$B$40/12*N7 -> 0
A96: Test if refinace is ok (0%) | B96: =E99*E47 -> 0 | D96: User Depreciation | E96: =SUM(F96:O96) -> 43000000 | F96: =+F43+F48+F53+F58+F63+F68+F73+F78 -> 1555555.6 | G96: =+G43+G48+G53+G58+G63+G68+G73+G78 -> 3933333.3 | H96: =+H43+H48+H53+H58+H63+H68+H73+H78 -> 5566666.7 | I96: =+I43+I48+I53+I58+I63+I68+I73+I78 -> 7316666.7 | J96: =+J43+J48+J53+J58+J63+J68+J73+J78 -> 9983333.3 | K96: =+K43+K48+K53+K58+K63+K68+K73+K78 -> 10983333 | L96: =+L43+L48+L53+L58+L63+L68+L73+L78 -> 3661111.1 | M96: =+M43+M48+M53+M58+M63+M68+M73+M78 -> 0 | ... O96: =+O43+O48+O53+O58+O63+O68+O73+O78 -> 0
A98: per sq. ft. | B98: =IFERROR(+E99/B90,0) -> 73.736885 | F98: =SUM(F95:F97) -> 2182288.9 | G98: =SUM(G95:G97) -> 5531503.3 | H98: =SUM(H95:H97) -> 7182611.7 | I98: =SUM(I95:I97) -> 8901209.2 | J98: =SUM(J95:J97) -> 11379461 | K98: =SUM(K95:K97) -> 11634096 | L98: =SUM(L95:L97) -> 3704495.3 | M98: =SUM(M95:M97) -> 0 | ... O98: =SUM(O95:O97) -> 0
A99: per sq. mtr | B99: =IFERROR(+E99/B91,0) -> 793.70383 | D99: Monthly Value | E99: =IFERROR(SUM(F95:O96)/E40,0) -> 701606.46
A104: Basic and project maintenance | B104: =F104+G104+H104+I104+J104+K104 -> 2500000 | F104: 1500000 | G104: 200000 | H104: 200000 | I104: 200000 | J104: 200000 | K104: 200000
A105: PM per sq. ft. per month | B105: =((B104/B21))/E3 -> 3.6492089
A106: PM per sq. mtr. per month | B106: =B105*10.764 -> 39.280084

Sheet Security Deposit
B8: Security Deposit | C8: Interest | D8: Remark
A9: Fitout Deposit | B9: 0 | C9: =+B9*'Rent Calculation'!F28/12*33.5 -> 0
A10: Security deposit | B10: ='Rent Calculation'!F67 -> 11418000 | C10: =+B10*'Rent Calculation'!F28/12*B16 -> 7193340
A11: Additional deposit | B11: ='Rent Calculation'!F71 -> 0 | C11: =+B11*'Rent Calculation'!F28/12*B16 -> 0
A12: Additional deposit (Electricity) | B12: =+'Rent Calculation'!F69 -> 500000 | C12: =+B12*'Rent Calculation'!F28*3 -> 157500
A13: Total | B13: =SUM(B9:B12) -> 11918000 | C13: =SUM(C9:C12) -> 7350840
A14: Area sqft | B14: ='Rent Calculation'!F21 -> 9515
A15: Rate for Carrying Cost | B15: ='Rent Calculation'!F28 -> 0.105
A16: Term Period in Months | B16: ='Rent Calculation'!F54 -> 72
A17: Rate per Sqft | C17: =C13/(B14*B16) -> 10.7299
A21: ARO working | B21: Per sqft | C21: Per sqmt
A22: Area (Sqft) | B22: ='Rent Calculation'!F21 -> 9515 | C22: ='Rent Calculation'!G21 -> 883.96507 | D22: ARO Cost per Sqft/pm
A23: ARO rate per Sqft as on 30.09.2017 | B23: =IF(B22<50000,82.6,62.72) -> 82.6 | C23: =B23*10.764 -> 889.1064 | D23: =B22*B23 -> 785939
D24: =D23/B16 -> 10915.819
D25: =D24/B22 -> 1.1472222
